Workbook
Name Slicer_countryname: #N/A
Name Slicer_Year_Opening: #N/A

Sheet Main
A1: RestaurantID | B1: RestaurantName | C1: CountryCode | D1: City | E1: Address | F1: Locality | G1: LocalityVerbose | H1: Longitude | I1: Latitude | J1: Cuisines | K1: Currency | L1: Has_Table_booking | M1: Has_Online_delivery | N1: Is_delivering_now | O1: Switch_to_order_menu | P1: Price_range | Q1: Votes | R1: Average_Cost_for_two | S1: Price_Bucket | T1: Rating | U1: Year Opening | V1: Month Opening | W1: Day Opening | X1: Datekey_Opening | Y1: Average_Cost_for_two_USD | Z1: countryname | AA1: Quarter
A2: 18435314 | B2: Punjabi's Veg Grill | C2: 1 | D2: New Delhi | E2: 13/288 , 14 Block Gurudwra, Geeta Colony, New Delhi | F2: Geeta Colony | G2: Geeta Colony, New Delhi | H2: 77.276769 | I2: 28.650775 | J2: North Indian | K2: Indian Rupees(Rs.) | L2: No | M2: No | N2: No | O2: No | P2: 1 | Q2: 0 | R2: 300 | S2: =IF(Table1[[#This Row],[Average_Cost_for_two]]<500,"Low",IF(Table1[[#This Row],[Average_Cost_for_two]]<=1500,"Medium","High")) -> Low | T2: 1 | U2: 2013 | V2: 9 | W2: 21 | X2: =IF(OR(Main!$U2=0, Main!$V2=0, Main!$W2=0), "", DATE(Main!$U2, Main!$V2, Main!$W2) ) -> 41538 | Y2: =Table1[[#This Row],[Average_Cost_for_two]]*VLOOKUP(Table1[[#This Row],[Currency]],currency!$A$2:$B$10,2,FALSE) -> 3.6 | Z2: =VLOOKUP(C2,country!A:B,2,FALSE) -> India | AA2: =ROUNDUP(V2/3,0) -> 3
A3: 18378015 | B3: Tasty Tandoor | C3: 1 | D3: New Delhi | E3: 726/2, Jheel Khuranja, Geeta Colony, New Delhi | F3: Geeta Colony | G3: Geeta Colony, New Delhi | H3: 77.275052 | I3: 28.658216 | J3: North Indian | K3: Indian Rupees(Rs.) | L3: No | M3: No | N3: No | O3: No | P3: 1 | Q3: 0 | R3: 200 | S3: =IF(Table1[[#This Row],[Average_Cost_for_two]]<500,"Low",IF(Table1[[#This Row],[Average_Cost_for_two]]<=1500,"Medium","High")) -> Low | T3: 1 | U3: 2016 | V3: 9 | W3: 10 | X3: =IF(OR(Main!$U3=0, Main!$V3=0, Main!$W3=0), "", DATE(Main!$U3, Main!$V3, Main!$W3) ) -> 42623 | Y3: =Table1[[#This Row],[Average_Cost_for_two]]*VLOOKUP(Table1[[#This Row],[Currency]],currency!$A$2:$B$10,2,FALSE) -> 2.4 | Z3: =VLOOKUP(C3,country!A:B,2,FALSE) -> India | AA3: =ROUNDUP(V3/3,0) -> 3
A4: 18424905 | B4: Taste of Spice | C4: 1 | D4: New Delhi | E4: C-222, Lajpat Nagar 1, New Delhi | F4: Lajpat Nagar 1 | G4: Lajpat Nagar 1, New Delhi | H4: 77.241312 | I4: 28.578311 | J4: North Indian | K4: Indian Rupees(Rs.) | L4: No | M4: Yes | N4: No | O4: No | P4: 1 | Q4: 0 | R4: 400 | S4: =IF(Table1[[#This Row],[Average_Cost_for_two]]<500,"Low",IF(Table1[[#This Row],[Average_Cost_for_two]]<=1500,"Medium","High")) -> Low | T4: 1 | U4: 2018 | V4: 9 | W4: 25 | X4: =IF(OR(Main!$U4=0, Main!$V4=0, Main!$W4=0), "", DATE(Main!$U4, Main!$V4, Main!$W4) ) -> 43368 | Y4: =Table1[[#This Row],[Average_Cost_for_two]]*VLOOKUP(Table1[[#This Row],[Currency]],currency!$A$2:$B$10,2,FALSE) -> 4.8 | Z4: =VLOOKUP(C4,country!A:B,2,FALSE) -> India | AA4: =ROUNDUP(V4/3,0) -> 3
A5: 18180072 | B5: Kolcata Bengali Dhaba | C5: 1 | D5: New Delhi | E5: Gali 7, Mahipalpur, New Delhi | F5: Mahipalpur | G5: Mahipalpur, New Delhi | H5: 77.123932 | I5: 28.543587 | J5: North Indian | K5: Indian Rupees(Rs.) | L5: No | M5: No | N5: No | O5: No | P5: 1 | Q5: 0 | R5: 100 | S5: =IF(Table1[[#This Row],[Average_Cost_for_two]]<500,"Low",IF(Table1[[#This Row],[Average_Cost_for_two]]<=1500,"Medium","High")) -> Low | T5: 1 | U5: 2018 | V5: 9 | W5: 6 | X5: =IF(OR(Main!$U5=0, Main!$V5=0, Main!$W5=0), "", DATE(Main!$U5, Main!$V5, Main!$W5) ) -> 43349 | Y5: =Table1[[#This Row],[Average_Cost_for_two]]*VLOOKUP(Table1[[#This Row],[Currency]],currency!$A$2:$B$10,2,FALSE) -> 1.2 | Z5: =VLOOKUP(C5,country!A:B,2,FALSE) -> India | AA5: =ROUNDUP(V5/3,0) -> 3
A6: 18415377 | B6: Sunil Punjabi Dhaba | C6: 1 | D6: New Delhi | E6: Main Vasant Kunj Road, Mahipalpur, New Delhi | F6: Mahipalpur | G6: Mahipalpur, New Delhi | H6: 77.129706 | I6: 28.541369 | J6: North Indian | K6: Indian Rupees(Rs.) | L6: No | M6: No | N6: No | O6: No | P6: 1 | Q6: 0 | R6: 150 | S6: =IF(Table1[[#This Row],[Average_Cost_for_two]]<500,"Low",IF(Table1[[#This Row],[Average_Cost_for_two]]<=1500,"Medium","High")) -> Low | T6: 1 | U6: 2013 | V6: 9 | W6: 17 | X6: =IF(OR(Main!$U6=0, Main!$V6=0, Main!$W6=0), "", DATE(Main!$U6, Main!$V6, Main!$W6) ) -> 41534 | Y6: =Table1[[#This Row],[Average_Cost_for_two]]*VLOOKUP(Table1[[#This Row],[Currency]],currency!$A$2:$B$10,2,FALSE) -> 1.8 | Z6: =VLOOKUP(C6,country!A:B,2,FALSE) -> India | AA6: =ROUNDUP(V6/3,0) -> 3
A7: 18421485 | B7: Bikaner Restaurant | C7: 1 | D7: New Delhi | E7: Shop 264, Near Hakikat Nagar, Mukherjee Nagar, New Delhi | F7: Mukherjee Nagar | G7: Mukherjee Nagar, New Delhi | H7: 77.208135 | I7: 28.699566 | J7: North Indian | K7: Indian Rupees(Rs.) | L7: No | M7: No | N7: No | O7: No | P7: 1 | Q7: 0 | R7: 100 | S7: =IF(Table1[[#This Row],[Average_Cost_for_two]]<500,"Low",IF(Table1[[#This Row],[Average_Cost_for_two]]<=1500,"Medium","High")) -> Low | T7: 1 | U7: 2018 | V7: 9 | W7: 3 | X7: =IF(OR(Main!$U7=0, Main!$V7=0, Main!$W7=0), "", DATE(Main!$U7, Main!$V7, Main!$W7) ) -> 43346 | Y7: =Table1[[#This Row],[Average_Cost_for_two]]*VLOOKUP(Table1[[#This Row],[Currency]],currency!$A$2:$B$10,2,FALSE) -> 1.2 | Z7: =VLOOKUP(C7,country!A:B,2,FALSE) -> India | AA7: =ROUNDUP(V7/3,0) -> 3
A8: 312413 | B8: Just In | C8: 1 | D8: New Delhi | E8: G-103, Vardhaman Mall, Mukherjee Nagar, New Delhi | F8: Mukherjee Nagar | G8: Mukherjee Nagar, New Delhi | H8: 77.219094 | I8: 28.70948 | J8: North Indian | K8: Indian Rupees(Rs.) | L8: No | M8: No | N8: No | O8: No | P8: 1 | Q8: 0 | R8: 200 | S8: =IF(Table1[[#This Row],[Average_Cost_for_two]]<500,"Low",IF(Table1[[#This Row],[Average_Cost_for_two]]<=1500,"Medium","High")) -> Low | T8: 1 | U8: 2011 | V8: 9 | W8: 16 | X8: =IF(OR(Main!$U8=0, Main!$V8=0, Main!$W8=0), "", DATE(Main!$U8, Main!$V8, Main!$W8) ) -> 40802 | Y8: =Table1[[#This Row],[Average_Cost_for_two]]*VLOOKUP(Table1[[#This Row],[Currency]],currency!$A$2:$B$10,2,FALSE) -> 2.4 | Z8: =VLOOKUP(C8,country!A:B,2,FALSE) -> India | AA8: =ROUNDUP(V8/3,0) -> 3
A9: 303497 | B9: Shri Shyam Ji Shudh Shakahari Bhojnalaya | C9: 1 | D9: New Delhi | E9: Khaira Mod, Najafgarh, New Delhi | F9: Najafgarh | G9: Najafgarh, New Delhi | H9: 76.974892 | I9: 28.611254 | J9: North Indian | K9: Indian Rupees(Rs.) | L9: No | M9: No | N9: No | O9: No | P9: 1 | Q9: 0 | R9: 150 | S9: =IF(Table1[[#This Row],[Average_Cost_for_two]]<500,"Low",IF(Table1[[#This Row],[Average_Cost_for_two]]<=1500,"Medium","High")) -> Low | T9: 1 | U9: 2014 | V9: 9 | W9: 21 | X9: =IF(OR(Main!$U9=0, Main!$V9=0, Main!$W9=0), "", DATE(Main!$U9, Main!$V9, Main!$W9) ) -> 41903 | Y9: =Table1[[#This Row],[Average_Cost_for_two]]*VLOOKUP(Table1[[#This Row],[Currency]],currency!$A$2:$B$10,2,FALSE) -> 1.8 | Z9: =VLOOKUP(C9,country!A:B,2,FALSE) -> India | AA9: =ROUNDUP(V9/3,0) -> 3
A10: 18354644 | B10: Shree Bhojnalaya | C10: 1 | D10: New Delhi | E10: Sarai Julena, Near Red Light, New Friends Colony, New Delhi | F10: New Friends Colony | G10: New Friends Colony, New Delhi | H10: 77.272762 | I10: 28.560771 | J10: North Indian | K10: Indian Rupees(Rs.) | L10: No | M10: No | N10: No | O10: No | P10: 1 | Q10: 0 | R10: 100 | S10: =IF(Table1[[#This Row],[Average_Cost_for_two]]<500,"Low",IF(Table1[[#This Row],[Average_Cost_for_two]]<=1500,"Medium","High")) -> Low | T10: 1 | U10: 2012 | V10: 9 | W10: 9 | X10: =IF(OR(Main!$U10=0, Main!$V10=0, Main!$W10=0), "", DATE(Main!$U10, Main!$V10, Main!$W10) ) -> 41161 | Y10: =Table1[[#This Row],[Average_Cost_for_two]]*VLOOKUP(Table1[[#This Row],[Currency]],currency!$A$2:$B$10,2,FALSE) -> 1.2 | Z10: =VLOOKUP(C10,country!A:B,2,FALSE) -> India | AA10: =ROUNDUP(V10/3,0) -> 3
A11: 18366001 | B11: Baba Ka Dhaba | C11: 1 | D11: New Delhi | E11: WZ-425, Main Road, Palam Colony, Opposite Railway Crossing, Palam, New Delhi | F11: Palam | G11: Palam, New Delhi | H11: 77.09028 | I11: 28.582898 | J11: North Indian | K11: Indian Rupees(Rs.) | L11: No | M11: No | N11: No | O11: No | P11: 1 | Q11: 0 | R11: 200 | S11: =IF(Table1[[#This Row],[Average_Cost_for_two]]<500,"Low",IF(Table1[[#This Row],[Average_Cost_for_two]]<=1500,"Medium","High")) -> Low | T11: 1 | U11: 2014 | V11: 9 | W11: 21 | X11: =IF(OR(Main!$U11=0, Main!$V11=0, Main!$W11=0), "", DATE(Main!$U11, Main!$V11, Main!$W11) ) -> 41903 | Y11: =Table1[[#This Row],[Average_Cost_for_two]]*VLOOKUP(Table1[[#This Row],[Currency]],currency!$A$2:$B$10,2,FALSE) -> 2.4 | Z11: =VLOOKUP(C11,country!A:B,2,FALSE) -> India | AA11: =ROUNDUP(V11/3,0) -> 3
A12: 18486845 | B12: Kaka Da Dhaba | C12: 1 | D12: New Delhi | E12: R.K. Puram Sector 12, R K Puram, New Delhi | F12: R K Puram | G12: R K Puram, New Delhi | H12: 77.174118 | I12: 28.577193 | J12: North Indian | K12: Indian Rupees(Rs.) | L12: No | M12: No | N12: No | O12: No | P12: 1 | Q12: 0 | R12: 100 | S12: =IF(Table1[[#This Row],[Average_Cost_for_two]]<500,"Low",IF(Table1[[#This Row],[Average_Cost_for_two]]<=1500,"Medium","High")) -> Low | T12: 1 | U12: 2012 | V12: 9 | W12: 24 | X12: =IF(OR(Main!$U12=0, Main!$V12=0, Main!$W12=0), "", DATE(Main!$U12, Main!$V12, Main!$W12) ) -> 41176 | Y12: =Table1[[#This Row],[Average_Cost_for_two]]*VLOOKUP(Table1[[#This Row],[Currency]],currency!$A$2:$B$10,2,FALSE) -> 1.2 | Z12: =VLOOKUP(C12,country!A:B,2,FALSE) -> India | AA12: =ROUNDUP(V12/3,0) -> 3
A13: 18424202 | B13: Famous Parantha and Poori Sabzi | C13: 1 | D13: New Delhi | E13: 44, Gali Number 1, Block A, New Ashok Nagar, Vasundhara Enclave, New Delhi | F13: Vasundhara Enclave | G13: Vasundhara Enclave, New Delhi | H13: 77.308509 | I13: 28.589376 | J13: North Indian | K13: Indian Rupees(Rs.) | L13: No | M13: No | N13: No | O13: No | P13: 1 | Q13: 0 | R13: 50 | S13: =IF(Table1[[#This Row],[Average_Cost_for_two]]<500,"Low",IF(Table1[[#This Row],[Average_Cost_for_two]]<=1500,"Medium","High")) -> Low | T13: 1 | U13: 2014 | V13: 9 | W13: 20 | X13: =IF(OR(Main!$U13=0, Main!$V13=0, Main!$W13=0), "", DATE(Main!$U13, Main!$V13, Main!$W13) ) -> 41902 | Y13: =Table1[[#This Row],[Average_Cost_for_two]]*VLOOKUP(Table1[[#This Row],[Currency]],currency!$A$2:$B$10,2,FALSE) -> 0.6 | Z13: =VLOOKUP(C13,country!A:B,2,FALSE) -> India | AA13: =ROUNDUP(V13/3,0) -> 3
... A8067: 49003 | B8067: SpiceKlub | C8067: 1 | D8067: Mumbai | E8067: 8A, Janta Industrial Estate, Opposite Phoenix Mills, Senapati Bapat Road, Lower Parel, Mumbai | F8067: Lower Parel | G8067: Lower Parel, Mumbai | H8067: 72.825553 | I8067: 18.994237 | J8067: North Indian | K8067: Indian Rupees(Rs.) | L8067: No | M8067: Yes | N8067: No | O8067: No | P8067: 3 | Q8067: 3370 | R8067: 1500 | S8067: =IF(Table1[[#This Row],[Average_Cost_for_two]]<500,"Low",IF(Table1[[#This Row],[Average_Cost_for_two]]<=1500,"Medium","High")) -> Medium | T8067: 4.2 | U8067: 2011 | V8067: 10 | W8067: 18 | X8067: =IF(OR(Main!$U8067=0, Main!$V8067=0, Main!$W8067=0), "", DATE(Main!$U8067, Main!$V8067, Main!$W8067) ) -> 40834 | Y8067: =Table1[[#This Row],[Average_Cost_for_two]]*VLOOKUP(Table1[[#This Row],[Currency]],currency!$A$2:$B$10,2,FALSE) -> 18 | Z8067: =VLOOKUP(C8067,country!A:B,2,FALSE) -> India | AA8067: =ROUNDUP(V8067/3,0) -> 4
A8068: 3400073 | B8068: The Latitude - Radisson Blu | C8068: 1 | D8068: Agra | E8068: Radisson Blu, Taj East Gate Road, Tajganj, Agra | F8068: Radisson Blu, Tajganj | G8068: Radisson Blu, Tajganj, Agra | H8068: 78.057044 | I8068: 27.163303 | J8068: North Indian, Chinese, Continental | K8068: Indian Rupees(Rs.) | L8068: No | M8068: No | N8068: No | O8068: No | P8068: 1 | Q8068: 103 | S8068: =IF(Table1[[#This Row],[Average_Cost_for_two]]<500,"Low",IF(Table1[[#This Row],[Average_Cost_for_two]]<=1500,"Medium","High")) -> Low | T8068: 3.9 | U8068: 2013 | V8068: 9 | W8068: 23 | X8068: =IF(OR(Main!$U8068=0, Main!$V8068=0, Main!$W8068=0), "", DATE(Main!$U8068, Main!$V8068, Main!$W8068) ) -> 41540 | Y8068: =Table1[[#This Row],[Average_Cost_for_two]]*VLOOKUP(Table1[[#This Row],[Currency]],currency!$A$2:$B$10,2,FALSE) -> 0 | Z8068: =VLOOKUP(C8068,country!A:B,2,FALSE) -> India | AA8068: =ROUNDUP(V8068/3,0) -> 3
A8069: 56618 | B8069: AB's - Absolute Barbecues | C8069: 1 | D8069: Bangalore | E8069: 90/4, 3rd Floor, Outer Ring Road, Munnekollaly Village, Marathahalli, Bangalore | F8069: Marathahalli | G8069: Marathahalli, Bangalore | H8069: 77.699386 | I8069: 12.949934 | J8069: European, Mediterranean, North Indian | K8069: Indian Rupees(Rs.) | L8069: No | M8069: No | N8069: No | O8069: No | P8069: 3 | Q8069: 6907 | R8069: 1400 | S8069: =IF(Table1[[#This Row],[Average_Cost_for_two]]<500,"Low",IF(Table1[[#This Row],[Average_Cost_for_two]]<=1500,"Medium","High")) -> Medium | T8069: 4.6 | U8069: 2011 | V8069: 9 | W8069: 21 | X8069: =IF(OR(Main!$U8069=0, Main!$V8069=0, Main!$W8069=0), "", DATE(Main!$U8069, Main!$V8069, Main!$W8069) ) -> 40807 | Y8069: =Table1[[#This Row],[Average_Cost_for_two]]*VLOOKUP(Table1[[#This Row],[Currency]],currency!$A$2:$B$10,2,FALSE) -> 16.8 | Z8069: =VLOOKUP(C8069,country!A:B,2,FALSE) -> India | AA8069: =ROUNDUP(V8069/3,0) -> 3
A8070: 2600180 | B8070: Indian Coffee House | C8070: 1 | D8070: Bhopal | E8070: Near Apex Bank, TT Nagar, Bhopal | F8070: TT Nagar | G8070: TT Nagar, Bhopal | H8070: 77.401663 | I8070: 23.234631 | J8070: South Indian | K8070: Indian Rupees(Rs.) | L8070: No | M8070: No | N8070: No | O8070: No | P8070: 2 | Q8070: 161 | R8070: 500 | S8070: =IF(Table1[[#This Row],[Average_Cost_for_two]]<500,"Low",IF(Table1[[#This Row],[Average_Cost_for_two]]<=1500,"Medium","High")) -> Medium | T8070: 3.9 | U8070: 2016 | V8070: 9 | W8070: 8 | X8070: =IF(OR(Main!$U8070=0, Main!$V8070=0, Main!$W8070=0), "", DATE(Main!$U8070, Main!$V8070, Main!$W8070) ) -> 42621 | Y8070: =Table1[[#This Row],[Average_Cost_for_two]]*VLOOKUP(Table1[[#This Row],[Currency]],currency!$A$2:$B$10,2,FALSE) -> 6 | Z8070: =VLOOKUP(C8070,country!A:B,2,FALSE) -> India | AA8070: =ROUNDUP(V8070/3,0) -> 3
A8071: 2600007 | B8071: Bake N Shake | C8071: 1 | D8071: Bhopal | E8071: Bhadbhada Road, Near Rang Mahal Talkies, TT Nagar, Bhopal | F8071: TT Nagar | G8071: TT Nagar, Bhopal | H8071: 77.398886 | I8071: 23.235123 | J8071: Fast Food | K8071: Indian Rupees(Rs.) | L8071: No | M8071: No | N8071: No | O8071: No | P8071: 2 | Q8071: 120 | R8071: 500 | S8071: =IF(Table1[[#This Row],[Average_Cost_for_two]]<500,"Low",IF(Table1[[#This Row],[Average_Cost_for_two]]<=1500,"Medium","High")) -> Medium | T8071: 4.3 | U8071: 2011 | V8071: 9 | W8071: 8 | X8071: =IF(OR(Main!$U8071=0, Main!$V8071=0, Main!$W8071=0), "", DATE(Main!$U8071, Main!$V8071, Main!$W8071) ) -> 40794 | Y8071: =Table1[[#This Row],[Average_Cost_for_two]]*VLOOKUP(Table1[[#This Row],[Currency]],currency!$A$2:$B$10,2,FALSE) -> 6 | Z8071: =VLOOKUP(C8071,country!A:B,2,FALSE) -> India | AA8071: =ROUNDUP(V8071/3,0) -> 3
A8072: 2900020 | B8072: Lal Qila | C8072: 1 | D8072: Bhubaneshwar | E8072: Sampark Vihar, Opposite Big Bazaar, KIIT Square, Patia, Bhubaneshwar | F8072: Patia | G8072: Patia, Bhubaneshwar | H8072: 85.82685 | I8072: 20.352992 | J8072: Mughlai, Chinese, North Indian | K8072: Indian Rupees(Rs.) | L8072: No | M8072: No | N8072: No | O8072: No | P8072: 2 | Q8072: 228 | R8072: 500 | S8072: =IF(Table1[[#This Row],[Average_Cost_for_two]]<500,"Low",IF(Table1[[#This Row],[Average_Cost_for_two]]<=1500,"Medium","High")) -> Medium | T8072: 3.7 | U8072: 2010 | V8072: 9 | W8072: 17 | X8072: =IF(OR(Main!$U8072=0, Main!$V8072=0, Main!$W8072=0), "", DATE(Main!$U8072, Main!$V8072, Main!$W8072) ) -> 40438 | Y8072: =Table1[[#This Row],[Average_Cost_for_two]]*VLOOKUP(Table1[[#This Row],[Currency]],currency!$A$2:$B$10,2,FALSE) -> 6 | Z8072: =VLOOKUP(C8072,country!A:B,2,FALSE) -> India | AA8072: =ROUNDUP(V8072/3,0) -> 3
A8073: 121312 | B8073: Mocha | C8073: 1 | D8073: Chandigarh | E8073: Ground Floor, Elante Mall, Phase 1, Chandigarh Industrial Area, Chandigarh | F8073: Elante Mall, Chandigarh Industrial Area | G8073: Elante Mall, Chandigarh Industrial Area, Chandigarh | H8073: 76.800865 | I8073: 30.705148 | J8073: Continental, Italian, Thai, Finger Food | K8073: Indian Rupees(Rs.) | L8073: No | M8073: No | N8073: No | O8073: No | P8073: 3 | Q8073: 428 | R8073: 1400 | S8073: =IF(Table1[[#This Row],[Average_Cost_for_two]]<500,"Low",IF(Table1[[#This Row],[Average_Cost_for_two]]<=1500,"Medium","High")) -> Medium | T8073: 4 | U8073: 2010 | V8073: 9 | W8073: 1 | X8073: =IF(OR(Main!$U8073=0, Main!$V8073=0, Main!$W8073=0), "", DATE(Main!$U8073, Main!$V8073, Main!$W8073) ) -> 40422 | Y8073: =Table1[[#This Row],[Average_Cost_for_two]]*VLOOKUP(Table1[[#This Row],[Currency]],currency!$A$2:$B$10,2,FALSE) -> 16.8 | Z8073: =VLOOKUP(C8073,country!A:B,2,FALSE) -> India | AA8073: =ROUNDUP(V8073/3,0) -> 3
A8074: 123125 | B8074: TGI Friday's | C8074: 1 | D8074: Chandigarh | E8074: SCO 51, Madhya Marg, Sector 26, Chandigarh | F8074: Sector 26 | G8074: Sector 26, Chandigarh | H8074: 76.806363 | I8074: 30.724943 | J8074: American, Tex-Mex | K8074: Indian Rupees(Rs.) | L8074: No | M8074: No | N8074: No | O8074: No | P8074: 3 | Q8074: 228 | R8074: 1800 | S8074: =IF(Table1[[#This Row],[Average_Cost_for_two]]<500,"Low",IF(Table1[[#This Row],[Average_Cost_for_two]]<=1500,"Medium","High")) -> High | T8074: 4.3 | U8074: 2013 | V8074: 9 | W8074: 3 | X8074: =IF(OR(Main!$U8074=0, Main!$V8074=0, Main!$W8074=0), "", DATE(Main!$U8074, Main!$V8074, Main!$W8074) ) -> 41520 | Y8074: =Table1[[#This Row],[Average_Cost_for_two]]*VLOOKUP(Table1[[#This Row],[Currency]],currency!$A$2:$B$10,2,FALSE) -> 21.6 | Z8074: =VLOOKUP(C8074,country!A:B,2,FALSE) -> India | AA8074: =ROUNDUP(V8074/3,0) -> 3
A8075: 307580 | B8075: Side Wok | C8075: 1 | D8075: Gurgaon | E8075: Ground Floor, MPD Tower, Opposite Magnolias, DLF 5, Golf Course Road, Gurgaon | F8075: Golf Course Road | G8075: Golf Course Road, Gurgaon | H8075: 77.097185 | I8075: 28.454919 | J8075: Burmese, Chinese, Japanese, Malaysian, Thai | K8075: Indian Rupees(Rs.) | L8075: Yes | M8075: Yes | N8075: No | O8075: No | P8075: 4 | Q8075: 280 | R8075: 2000 | S8075: =IF(Table1[[#This Row],[Average_Cost_for_two]]<500,"Low",IF(Table1[[#This Row],[Average_Cost_for_two]]<=1500,"Medium","High")) -> High | T8075: 3.9 | U8075: 2017 | V8075: 8 | W8075: 7 | X8075: =IF(OR(Main!$U8075=0, Main!$V8075=0, Main!$W8075=0), "", DATE(Main!$U8075, Main!$V8075, Main!$W8075) ) -> 42954 | Y8075: =Table1[[#This Row],[Average_Cost_for_two]]*VLOOKUP(Table1[[#This Row],[Currency]],currency!$A$2:$B$10,2,FALSE) -> 24 | Z8075: =VLOOKUP(C8075,country!A:B,2,FALSE) -> India | AA8075: =ROUNDUP(V8075/3,0) -> 3
A8076: 7518 | B8076: Spiritual Bar & Lounge-DoubleTree by Hilton | C8076: 1 | D8076: Gurgaon | E8076: DoubleTree by Hilton, Golf Course Road, Sector 56, Gurgaon | F8076: DoubleTree by Hilton, Sector 56 | G8076: DoubleTree by Hilton, Sector 56, Gurgaon | H8076: 77.104693 | I8076: 28.422147 | J8076: Pizza, Italian | K8076: Indian Rupees(Rs.) | L8076: Yes | M8076: No | N8076: No | O8076: No | P8076: 4 | Q8076: 52 | R8076: 2000 | S8076: =IF(Table1[[#This Row],[Average_Cost_for_two]]<500,"Low",IF(Table1[[#This Row],[Average_Cost_for_two]]<=1500,"Medium","High")) -> High | T8076: 3.4 | U8076: 2010 | V8076: 6 | W8076: 16 | X8076: =IF(OR(Main!$U8076=0, Main!$V8076=0, Main!$W8076=0), "", DATE(Main!$U8076, Main!$V8076, Main!$W8076) ) -> 40345 | Y8076: =Table1[[#This Row],[Average_Cost_for_two]]*VLOOKUP(Table1[[#This Row],[Currency]],currency!$A$2:$B$10,2,FALSE) -> 24 | Z8076: =VLOOKUP(C8076,country!A:B,2,FALSE) -> India | AA8076: =ROUNDUP(V8076/3,0) -> 2
A8077: 18446415 | B8077: The Old School Brew House | C8077: 1 | D8077: Gurgaon | E8077: SCO 56, 4th Floor, Sector 29, Gurgaon | F8077: Sector 29 | G8077: Sector 29, Gurgaon | H8077: 77.064195 | I8077: 28.467777 | J8077: Continental, Burger, Pizza, North Indian, European, Finger Food | K8077: Indian Rupees(Rs.) | L8077: Yes | M8077: No | N8077: No | O8077: No | P8077: 4 | Q8077: 96 | R8077: 2000 | S8077: =IF(Table1[[#This Row],[Average_Cost_for_two]]<500,"Low",IF(Table1[[#This Row],[Average_Cost_for_two]]<=1500,"Medium","High")) -> High | T8077: 3.9 | U8077: 2011 | V8077: 6 | W8077: 1 | X8077: =IF(OR(Main!$U8077=0, Main!$V8077=0, Main!$W8077=0), "", DATE(Main!$U8077, Main!$V8077, Main!$W8077) ) -> 40695 | Y8077: =Table1[[#This Row],[Average_Cost_for_two]]*VLOOKUP(Table1[[#This Row],[Currency]],currency!$A$2:$B$10,2,FALSE) -> 24 | Z8077: =VLOOKUP(C8077,country!A:B,2,FALSE) -> India | AA8077: =ROUNDUP(V8077/3,0) -> 2
A8078: 306134 | B8078: The Wine Company | C8078: 1 | D8078: Gurgaon | E8078: Cyber Hub, DLF Cyber City, Gurgaon | F8078: Cyber Hub, DLF Cyber City | G8078: Cyber Hub, DLF Cyber City, Gurgaon | H8078: 77.089048 | I8078: 28.496229 | J8078: Italian, European | K8078: Indian Rupees(Rs.) | L8078: Yes | M8078: No | N8078: No | O8078: No | P8078: 4 | Q8078: 2412 | R8078: 2000 | S8078: =IF(Table1[[#This Row],[Average_Cost_for_two]]<500,"Low",IF(Table1[[#This Row],[Average_Cost_for_two]]<=1500,"Medium","High")) -> High | T8078: 2.4 | U8078: 2016 | V8078: 5 | W8078: 23 | X8078: =IF(OR(Main!$U8078=0, Main!$V8078=0, Main!$W8078=0), "", DATE(Main!$U8078, Main!$V8078, Main!$W8078) ) -> 42513 | Y8078: =Table1[[#This Row],[Average_Cost_for_two]]*VLOOKUP(Table1[[#This Row],[Currency]],currency!$A$2:$B$10,2,FALSE) -> 24 | Z8078: =VLOOKUP(C8078,country!A:B,2,FALSE) -> India | AA8078: =ROUNDUP(V8078/3,0) -> 2
A8079: 1401934 | B8079: Mama Loca | C8079: 1 | D8079: Indore | E8079: G-1, Princess Centre, 6/3, New Palasia, Indore | F8079: New Palasia | G8079: New Palasia, Indore | H8079: 75.884212 | I8079: 22.728163 | J8079: Greek, Lebanese | K8079: Indian Rupees(Rs.) | L8079: No | M8079: No | N8079: No | O8079: No | P8079: 3 | Q8079: 304 | R8079: 1000 | S8079: =IF(Table1[[#This Row],[Average_Cost_for_two]]<500,"Low",IF(Table1[[#This Row],[Average_Cost_for_two]]<=1500,"Medium","High")) -> Medium | T8079: 4.2 | U8079: 2016 | V8079: 9 | W8079: 25 | X8079: =IF(OR(Main!$U8079=0, Main!$V8079=0, Main!$W8079=0), "", DATE(Main!$U8079, Main!$V8079, Main!$W8079) ) -> 42638 | Y8079: =Table1[[#This Row],[Average_Cost_for_two]]*VLOOKUP(Table1[[#This Row],[Currency]],currency!$A$2:$B$10,2,FALSE) -> 12 | Z8079: =VLOOKUP(C8079,country!A:B,2,FALSE) -> India | AA8079: =ROUNDUP(V8079/3,0) -> 3
A8080: 18395137 | B8080: Just My Bakes | C8080: 1 | D8080: Indore | E8080: 5-B/F, Scheme 74C, Vijay Nagar, Indore | F8080: Vijay Nagar | G8080: Vijay Nagar, Indore | H8080: 75.892574 | I8080: 22.760072 | J8080: Cafe, Bakery | K8080: Indian Rupees(Rs.) | L8080: No | M8080: No | N8080: No | O8080: No | P8080: 2 | Q8080: 69 | R8080: 500 | S8080: =IF(Table1[[#This Row],[Average_Cost_for_two]]<500,"Low",IF(Table1[[#This Row],[Average_Cost_for_two]]<=1500,"Medium","High")) -> Medium | T8080: 3.9 | U8080: 2010 | V8080: 9 | W8080: 14 | X8080: =IF(OR(Main!$U8080=0, Main!$V8080=0, Main!$W8080=0), "", DATE(Main!$U8080, Main!$V8080, Main!$W8080) ) -> 40435 | Y8080: =Table1[[#This Row],[Average_Cost_for_two]]*VLOOKUP(Table1[[#This Row],[Currency]],currency!$A$2:$B$10,2,FALSE) -> 6 | Z8080: =VLOOKUP(C8080,country!A:B,2,FALSE) -> India | AA8080: =ROUNDUP(V8080/3,0) -> 3
... A8084: 2300483 | B8084: The Zaffran | C8084: 1 | D8084: Kanpur | E8084: Ratan Zone, Coca-Cola Crossing, Ashok Nagar, Kanpur | F8084: Ashok Nagar | G8084: Ashok Nagar, Kanpur | H8084: 80.313564 | I8084: 26.471617 | J8084: North Indian, Continental, Asian | K8084: Indian Rupees(Rs.) | L8084: No | M8084: No | N8084: No | O8084: No | P8084: 3 | Q8084: 51 | R8084: 800 | S8084: =IF(Table1[[#This Row],[Average_Cost_for_two]]<500,"Low",IF(Table1[[#This Row],[Average_Cost_for_two]]<=1500,"Medium","High")) -> Medium | T8084: 3.3 | U8084: 2014 | V8084: 9 | W8084: 23 | X8084: =IF(OR(Main!$U8084=0, Main!$V8084=0, Main!$W8084=0), "", DATE(Main!$U8084, Main!$V8084, Main!$W8084) ) -> 41905 | Y8084: =Table1[[#This Row],[Average_Cost_for_two]]*VLOOKUP(Table1[[#This Row],[Currency]],currency!$A$2:$B$10,2,FALSE) -> 9.6 | Z8084: =VLOOKUP(C8084,country!A:B,2,FALSE) -> India | AA8084: =ROUNDUP(V8084/3,0) -> 3
A8085: 18312106 | B8085: UrbanCrave | C8085: 1 | D8085: Kanpur | E8085: 14/125, The Mall, Mall Road, Colonelganj, Parade, Kanpur | F8085: Parade | G8085: Parade, Kanpur | H8085: 80.342796 | I8085: 26.474986 | J8085: Cafe, Continental, Desserts, Ice Cream, Italian, Beverages | K8085: Indian Rupees(Rs.) | L8085: No | M8085: No | N8085: No | O8085: No | P8085: 1 | Q8085: 127 | S8085: =IF(Table1[[#This Row],[Average_Cost_for_two]]<500,"Low",IF(Table1[[#This Row],[Average_Cost_for_two]]<=1500,"Medium","High")) -> Low | T8085: 3.9 | U8085: 2014 | V8085: 9 | W8085: 19 | X8085: =IF(OR(Main!$U8085=0, Main!$V8085=0, Main!$W8085=0), "", DATE(Main!$U8085, Main!$V8085, Main!$W8085) ) -> 41901 | Y8085: =Table1[[#This Row],[Average_Cost_for_two]]*VLOOKUP(Table1[[#This Row],[Currency]],currency!$A$2:$B$10,2,FALSE) -> 0 | Z8085: =VLOOKUP(C8085,country!A:B,2,FALSE) -> India | AA8085: =ROUNDUP(V8085/3,0) -> 3
A8086: 900800 | B8086: ChaiCofi | C8086: 1 | D8086: Kochi | E8086: Arammal Tower, Near Express Garden, KK Road, Kaloor, Kochi | F8086: Kaloor | G8086: Kaloor, Kochi | H8086: 76.293136 | I8086: 9.9917028 | J8086: Cafe, Continental, Italian | K8086: Indian Rupees(Rs.) | L8086: No | M8086: No | N8086: No | O8086: No | P8086: 2 | Q8086: 160 | R8086: 800 | S8086: =IF(Table1[[#This Row],[Average_Cost_for_two]]<500,"Low",IF(Table1[[#This Row],[Average_Cost_for_two]]<=1500,"Medium","High")) -> Medium | T8086: 4 | U8086: 2010 | V8086: 9 | W8086: 7 | X8086: =IF(OR(Main!$U8086=0, Main!$V8086=0, Main!$W8086=0), "", DATE(Main!$U8086, Main!$V8086, Main!$W8086) ) -> 40428 | Y8086: =Table1[[#This Row],[Average_Cost_for_two]]*VLOOKUP(Table1[[#This Row],[Currency]],currency!$A$2:$B$10,2,FALSE) -> 9.6 | Z8086: =VLOOKUP(C8086,country!A:B,2,FALSE) -> India | AA8086: =ROUNDUP(V8086/3,0) -> 3
A8087: 800468 | B8087: Grandson of Tunday Kababi | C8087: 1 | D8087: Lucknow | E8087: Naaz Cinema Road, Aminabad, Lucknow | F8087: Aminabad | G8087: Aminabad, Lucknow | H8087: 80.927431 | I8087: 26.848506 | J8087: Mughlai, Lucknowi | K8087: Indian Rupees(Rs.) | L8087: No | M8087: No | N8087: No | O8087: No | P8087: 1 | Q8087: 1057 | R8087: 300 | S8087: =IF(Table1[[#This Row],[Average_Cost_for_two]]<500,"Low",IF(Table1[[#This Row],[Average_Cost_for_two]]<=1500,"Medium","High")) -> Low | T8087: 4.9 | U8087: 2013 | V8087: 9 | W8087: 20 | X8087: =IF(OR(Main!$U8087=0, Main!$V8087=0, Main!$W8087=0), "", DATE(Main!$U8087, Main!$V8087, Main!$W8087) ) -> 41537 | Y8087: =Table1[[#This Row],[Average_Cost_for_two]]*VLOOKUP(Table1[[#This Row],[Currency]],currency!$A$2:$B$10,2,FALSE) -> 3.6 | Z8087: =VLOOKUP(C8087,country!A:B,2,FALSE) -> India | AA8087: =ROUNDUP(V8087/3,0) -> 3
A8088: 18375866 | B8088: Free Spirit | C8088: 1 | D8088: Lucknow | E8088: Indira Gandhi Pratishthan-Kathauta Chauraha road, Near Shaheed Path Flyover, Vishesh Khand 2, Gomti Nagar, Lucknow | F8088: Gomti Nagar | G8088: Gomti Nagar, Lucknow | H8088: 81.015159 | I8088: 26.867445 | J8088: Cafe, Italian | K8088: Indian Rupees(Rs.) | L8088: No | M8088: No | N8088: No | O8088: No | P8088: 2 | Q8088: 106 | R8088: 450 | S8088: =IF(Table1[[#This Row],[Average_Cost_for_two]]<500,"Low",IF(Table1[[#This Row],[Average_Cost_for_two]]<=1500,"Medium","High")) -> Low | T8088: 4.3 | U8088: 2014 | V8088: 9 | W8088: 28 | X8088: =IF(OR(Main!$U8088=0, Main!$V8088=0, Main!$W8088=0), "", DATE(Main!$U8088, Main!$V8088, Main!$W8088) ) -> 41910 | Y8088: =Table1[[#This Row],[Average_Cost_for_two]]*VLOOKUP(Table1[[#This Row],[Currency]],currency!$A$2:$B$10,2,FALSE) -> 5.4 | Z8088: =VLOOKUP(C8088,country!A:B,2,FALSE) -> India | AA8088: =ROUNDUP(V8088/3,0) -> 3
A8089: 3100010 | B8089: Diesel Cafe | C8089: 1 | D8089: Mangalore | E8089: Ground Floor, Hotel Prestige, Near Collector's Gate, Balmatta, Mangalore | F8089: Balmatta | G8089: Balmatta, Mangalore | H8089: 74.852744 | I8089: 12.873678 | J8089: American, Italian | K8089: Indian Rupees(Rs.) | L8089: No | M8089: No | N8089: No | O8089: No | P8089: 3 | Q8089: 196 | R8089: 900 | S8089: =IF(Table1[[#This Row],[Average_Cost_for_two]]<500,"Low",IF(Table1[[#This Row],[Average_Cost_for_two]]<=1500,"Medium","High")) -> Medium | T8089: 3.8 | U8089: 2013 | V8089: 9 | W8089: 19 | X8089: =IF(OR(Main!$U8089=0, Main!$V8089=0, Main!$W8089=0), "", DATE(Main!$U8089, Main!$V8089, Main!$W8089) ) -> 41536 | Y8089: =Table1[[#This Row],[Average_Cost_for_two]]*VLOOKUP(Table1[[#This Row],[Currency]],currency!$A$2:$B$10,2,FALSE) -> 10.8 | Z8089: =VLOOKUP(C8089,country!A:B,2,FALSE) -> India | AA8089: =ROUNDUP(V8089/3,0) -> 3
A8090: 3100145 | B8090: Froth On Top | C8090: 1 | D8090: Mangalore | E8090: Silk House, Balmatta Arya Samaj Road, Balmatta, Mangalore | F8090: Balmatta | G8090: Balmatta, Mangalore | H8090: 74.851586 | I8090: 12.873531 | J8090: Chinese, Mangalorean | K8090: Indian Rupees(Rs.) | L8090: No | M8090: No | N8090: No | O8090: No | P8090: 2 | Q8090: 355 | R8090: 700 | S8090: =IF(Table1[[#This Row],[Average_Cost_for_two]]<500,"Low",IF(Table1[[#This Row],[Average_Cost_for_two]]<=1500,"Medium","High")) -> Medium | T8090: 3.7 | U8090: 2016 | V8090: 9 | W8090: 19 | X8090: =IF(OR(Main!$U8090=0, Main!$V8090=0, Main!$W8090=0), "", DATE(Main!$U8090, Main!$V8090, Main!$W8090) ) -> 42632 | Y8090: =Table1[[#This Row],[Average_Cost_for_two]]*VLOOKUP(Table1[[#This Row],[Currency]],currency!$A$2:$B$10,2,FALSE) -> 8.4 | Z8090: =VLOOKUP(C8090,country!A:B,2,FALSE) -> India | AA8090: =ROUNDUP(V8090/3,0) -> 3
A8091: 18233317 | B8091: 145 Kala Ghoda | C8091: 1 | D8091: Mumbai | E8091: 145, Kala Ghoda, Fort, Mumbai | F8091: Fort | G8091: Fort, Mumbai | H8091: 72.832585 | I8091: 18.927584 | J8091: Fast Food, Beverages, Desserts | K8091: Indian Rupees(Rs.) | L8091: No | M8091: No | N8091: No | O8091: No | P8091: 3 | Q8091: 1606 | R8091: 1500 | S8091: =IF(Table1[[#This Row],[Average_Cost_for_two]]<500,"Low",IF(Table1[[#This Row],[Average_Cost_for_two]]<=1500,"Medium","High")) -> Medium | T8091: 4.2 | U8091: 2012 | V8091: 9 | W8091: 5 | X8091: =IF(OR(Main!$U8091=0, Main!$V8091=0, Main!$W8091=0), "", DATE(Main!$U8091, Main!$V8091, Main!$W8091) ) -> 41157 | Y8091: =Table1[[#This Row],[Average_Cost_for_two]]*VLOOKUP(Table1[[#This Row],[Currency]],currency!$A$2:$B$10,2,FALSE) -> 18 | Z8091: =VLOOKUP(C8091,country!A:B,2,FALSE) -> India | AA8091: =ROUNDUP(V8091/3,0) -> 3
A8092: 3600265 | B8092: Jalpaan Dining Saga | C8092: 1 | D8092: Mysore | E8092: 366, 2nd & 3rd Floor, Near Ramaswamy Circle, Chamaraja Mohalla, Chamrajpura, Mysore | F8092: Chamrajpura | G8092: Chamrajpura, Mysore | H8092: 76.643622 | I8092: 12.304569 | J8092: North Indian, Chinese, Italian | K8092: Indian Rupees(Rs.) | L8092: No | M8092: No | N8092: No | O8092: No | P8092: 3 | Q8092: 172 | R8092: 900 | S8092: =IF(Table1[[#This Row],[Average_Cost_for_two]]<500,"Low",IF(Table1[[#This Row],[Average_Cost_for_two]]<=1500,"Medium","High")) -> Medium | T8092: 3.7 | U8092: 2016 | V8092: 9 | W8092: 8 | X8092: =IF(OR(Main!$U8092=0, Main!$V8092=0, Main!$W8092=0), "", DATE(Main!$U8092, Main!$V8092, Main!$W8092) ) -> 42621 | Y8092: =Table1[[#This Row],[Average_Cost_for_two]]*VLOOKUP(Table1[[#This Row],[Currency]],currency!$A$2:$B$10,2,FALSE) -> 10.8 | Z8092: =VLOOKUP(C8092,country!A:B,2,FALSE) -> India | AA8092: =ROUNDUP(V8092/3,0) -> 3
A8093: 18441771 | B8093: The Ark | C8093: 1 | D8093: Gurgaon | E8093: Address One, Second Floor, Next to Hilton Double Tree Hotel, Baani, Sector 56, Golf Course Road, Gurgaon | F8093: Golf Course Road | G8093: Golf Course Road, Gurgaon | H8093: 77.105038 | I8093: 28.421812 | J8093: Seafood, Mediterranean | K8093: Indian Rupees(Rs.) | L8093: Yes | M8093: No | N8093: No | O8093: No | P8093: 4 | Q8093: 45 | R8093: 2000 | S8093: =IF(Table1[[#This Row],[Average_Cost_for_two]]<500,"Low",IF(Table1[[#This Row],[Average_Cost_for_two]]<=1500,"Medium","High")) -> High | T8093: 3.7 | U8093: 2017 | V8093: 5 | W8093: 24 | X8093: =IF(OR(Main!$U8093=0, Main!$V8093=0, Main!$W8093=0), "", DATE(Main!$U8093, Main!$V8093, Main!$W8093) ) -> 42879 | Y8093: =Table1[[#This Row],[Average_Cost_for_two]]*VLOOKUP(Table1[[#This Row],[Currency]],currency!$A$2:$B$10,2,FALSE) -> 24 | Z8093: =VLOOKUP(C8093,country!A:B,2,FALSE) -> India | AA8093: =ROUNDUP(V8093/3,0) -> 2
A8094: 3600361 | B8094: Tandooriwala | C8094: 1 | D8094: Mysore | E8094: 26, 1st Stage, KHB, Nrupathunga Road, Kuvempunagar, Mysore | F8094: Kuvempunagar | G8094: Kuvempunagar, Mysore | H8094: 76.625861 | I8094: 12.284747 | J8094: North Indian | K8094: Indian Rupees(Rs.) | L8094: No | M8094: No | N8094: No | O8094: No | P8094: 2 | Q8094: 127 | R8094: 700 | S8094: =IF(Table1[[#This Row],[Average_Cost_for_two]]<500,"Low",IF(Table1[[#This Row],[Average_Cost_for_two]]<=1500,"Medium","High")) -> Medium | T8094: 3.5 | U8094: 2014 | V8094: 9 | W8094: 8 | X8094: =IF(OR(Main!$U8094=0, Main!$V8094=0, Main!$W8094=0), "", DATE(Main!$U8094, Main!$V8094, Main!$W8094) ) -> 41890 | Y8094: =Table1[[#This Row],[Average_Cost_for_two]]*VLOOKUP(Table1[[#This Row],[Currency]],currency!$A$2:$B$10,2,FALSE) -> 8.4 | Z8094: =VLOOKUP(C8094,country!A:B,2,FALSE) -> India | AA8094: =ROUNDUP(V8094/3,0) -> 3
A8095: 3600072 | B8095: Nanking | C8095: 1 | D8095: Mysore | E8095: High Tension Double Road, Near Vidyavardhaka College, 2nd Stage, Vijay Nagar, Mysore | F8095: Vijay Nagar | G8095: Vijay Nagar, Mysore | H8095: 76.617889 | I8095: 12.337928 | J8095: Chinese, Thai | K8095: Indian Rupees(Rs.) | L8095: No | M8095: No | N8095: No | O8095: No | P8095: 2 | Q8095: 208 | R8095: 550 | S8095: =IF(Table1[[#This Row],[Average_Cost_for_two]]<500,"Low",IF(Table1[[#This Row],[Average_Cost_for_two]]<=1500,"Medium","High")) -> Medium | T8095: 3.7 | U8095: 2011 | V8095: 9 | W8095: 16 | X8095: =IF(OR(Main!$U8095=0, Main!$V8095=0, Main!$W8095=0), "", DATE(Main!$U8095, Main!$V8095, Main!$W8095) ) -> 40802 | Y8095: =Table1[[#This Row],[Average_Cost_for_two]]*VLOOKUP(Table1[[#This Row],[Currency]],currency!$A$2:$B$10,2,FALSE) -> 6.6 | Z8095: =VLOOKUP(C8095,country!A:B,2,FALSE) -> India | AA8095: =ROUNDUP(V8095/3,0) -> 3
A8096: 1600067 | B8096: Al Arabian Express | C8096: 1 | D8096: Nashik | E8096: Near Big Bazar, College Road, Nashik | F8096: College Road | G8096: College Road, Nashik | H8096: 73.765043 | I8096: 20.003734 | J8096: Mughlai | K8096: Indian Rupees(Rs.) | L8096: No | M8096: No | N8096: No | O8096: No | P8096: 3 | Q8096: 162 | R8096: 500 | S8096: =IF(Table1[[#This Row],[Average_Cost_for_two]]<500,"Low",IF(Table1[[#This Row],[Average_Cost_for_two]]<=1500,"Medium","High")) -> Medium | T8096: 3.7 | U8096: 2018 | V8096: 9 | W8096: 21 | X8096: =IF(OR(Main!$U8096=0, Main!$V8096=0, Main!$W8096=0), "", DATE(Main!$U8096, Main!$V8096, Main!$W8096) ) -> 43364 | Y8096: =Table1[[#This Row],[Average_Cost_for_two]]*VLOOKUP(Table1[[#This Row],[Currency]],currency!$A$2:$B$10,2,FALSE) -> 6 | Z8096: =VLOOKUP(C8096,country!A:B,2,FALSE) -> India | AA8096: =ROUNDUP(V8096/3,0) -> 3
A8097: 3700408 | B8097: Italize | C8097: 1 | D8097: Puducherry | E8097: 137, 1st Floor, Mission Street (kosakadai street cutting), MG Road, Puducherry | F8097: MG Road | G8097: MG Road, Puducherry | H8097: 79.831348 | I8097: 11.936488 | J8097: Pizza, Italian | K8097: Indian Rupees(Rs.) | L8097: No | M8097: No | N8097: No | O8097: No | P8097: 3 | Q8097: 97 | R8097: 600 | S8097: =IF(Table1[[#This Row],[Average_Cost_for_two]]<500,"Low",IF(Table1[[#This Row],[Average_Cost_for_two]]<=1500,"Medium","High")) -> Medium | T8097: 3.6 | U8097: 2014 | V8097: 9 | W8097: 15 | X8097: =IF(OR(Main!$U8097=0, Main!$V8097=0, Main!$W8097=0), "", DATE(Main!$U8097, Main!$V8097, Main!$W8097) ) -> 41897 | Y8097: =Table1[[#This Row],[Average_Cost_for_two]]*VLOOKUP(Table1[[#This Row],[Currency]],currency!$A$2:$B$10,2,FALSE) -> 7.2 | Z8097: =VLOOKUP(C8097,country!A:B,2,FALSE) -> India | AA8097: =ROUNDUP(V8097/3,0) -> 3
... A8319: 15705 | B8319: Kitchen At 95 - Hyatt Regency | C8319: 1 | D8319: Ludhiana | E8319: Hyatt Regency, Site 4, Ferozepur Road, Rajguru Nagar, Ludhiana | F8319: Hyatt Regency, Rajguru Nagar | G8319: Hyatt Regency, Rajguru Nagar, Ludhiana | H8319: 75.786976 | I8319: 30.885814 | J8319: Mediterranean, Chinese, Continental | K8319: Indian Rupees(Rs.) | L8319: No | M8319: No | N8319: No | O8319: No | P8319: 4 | Q8319: 87 | R8319: 2000 | S8319: =IF(Table1[[#This Row],[Average_Cost_for_two]]<500,"Low",IF(Table1[[#This Row],[Average_Cost_for_two]]<=1500,"Medium","High")) -> High | T8319: 4.3 | U8319: 2017 | V8319: 10 | W8319: 17 | X8319: =IF(OR(Main!$U8319=0, Main!$V8319=0, Main!$W8319=0), "", DATE(Main!$U8319, Main!$V8319, Main!$W8319) ) -> 43025 | Y8319: =Table1[[#This Row],[Average_Cost_for_two]]*VLOOKUP(Table1[[#This Row],[Currency]],currency!$A$2:$B$10,2,FALSE) -> 24 | Z8319: =VLOOKUP(C8319,country!A:B,2,FALSE) -> India | AA8319: =ROUNDUP(V8319/3,0) -> 4
A8320: 3400346 | B8320: Sheroes Hangout | C8320: 1 | D8320: Agra | E8320: Opposite The Gateway Hotel, Fatehabad Road, Tajganj, Agra | F8320: Tajganj | G8320: Tajganj, Agra | H8320: 78.040165 | I8320: 27.16185 | J8320: Cafe, North Indian, Chinese | K8320: Indian Rupees(Rs.) | L8320: No | M8320: No | N8320: No | O8320: No | P8320: 1 | Q8320: 77 | S8320: =IF(Table1[[#This Row],[Average_Cost_for_two]]<500,"Low",IF(Table1[[#This Row],[Average_Cost_for_two]]<=1500,"Medium","High")) -> Low | T8320: 4.9 | U8320: 2015 | V8320: 3 | W8320: 7 | X8320: =IF(OR(Main!$U8320=0, Main!$V8320=0, Main!$W8320=0), "", DATE(Main!$U8320, Main!$V8320, Main!$W8320) ) -> 42070 | Y8320: =Table1[[#This Row],[Average_Cost_for_two]]*VLOOKUP(Table1[[#This Row],[Currency]],currency!$A$2:$B$10,2,FALSE) -> 0 | Z8320: =VLOOKUP(C8320,country!A:B,2,FALSE) -> India | AA8320: =ROUNDUP(V8320/3,0) -> 1
A8321: 2200030 | B8321: Crystal Restaurant | C8321: 1 | D8321: Amritsar | E8321: Crystal Chowk, Queens Road, INA Colony, Amritsar | F8321: INA Colony | G8321: INA Colony, Amritsar | H8321: 74.875878 | I8321: 31.635658 | J8321: North Indian, Mughlai | K8321: Indian Rupees(Rs.) | L8321: No | M8321: No | N8321: No | O8321: No | P8321: 3 | Q8321: 122 | R8321: 800 | S8321: =IF(Table1[[#This Row],[Average_Cost_for_two]]<500,"Low",IF(Table1[[#This Row],[Average_Cost_for_two]]<=1500,"Medium","High")) -> Medium | T8321: 3.4 | U8321: 2017 | V8321: 3 | W8321: 12 | X8321: =IF(OR(Main!$U8321=0, Main!$V8321=0, Main!$W8321=0), "", DATE(Main!$U8321, Main!$V8321, Main!$W8321) ) -> 42806 | Y8321: =Table1[[#This Row],[Average_Cost_for_two]]*VLOOKUP(Table1[[#This Row],[Currency]],currency!$A$2:$B$10,2,FALSE) -> 9.6 | Z8321: =VLOOKUP(C8321,country!A:B,2,FALSE) -> India | AA8321: =ROUNDUP(V8321/3,0) -> 1
A8322: 2200283 | B8322: Sakhis Watz Kukin | C8322: 1 | D8322: Amritsar | E8322: M 47, Green Avenue, opp Main Park, Amritsar | F8322: Ranjit Avenue | G8322: Ranjit Avenue, Amritsar | H8322: 74.86491 | I8322: 31.646689 | J8322: North Indian, Chinese | K8322: Indian Rupees(Rs.) | L8322: No | M8322: No | N8322: No | O8322: No | P8322: 2 | Q8322: 51 | R8322: 700 | S8322: =IF(Table1[[#This Row],[Average_Cost_for_two]]<500,"Low",IF(Table1[[#This Row],[Average_Cost_for_two]]<=1500,"Medium","High")) -> Medium | T8322: 3.6 | U8322: 2014 | V8322: 3 | W8322: 1 | X8322: =IF(OR(Main!$U8322=0, Main!$V8322=0, Main!$W8322=0), "", DATE(Main!$U8322, Main!$V8322, Main!$W8322) ) -> 41699 | Y8322: =Table1[[#This Row],[Average_Cost_for_two]]*VLOOKUP(Table1[[#This Row],[Currency]],currency!$A$2:$B$10,2,FALSE) -> 8.4 | Z8322: =VLOOKUP(C8322,country!A:B,2,FALSE) -> India | AA8322: =ROUNDUP(V8322/3,0) -> 1
A8323: 2200149 | B8323: Shudh Restaurant | C8323: 1 | D8323: Amritsar | E8323: Opposite Gurudwara Saragarhi, Near Dharm Singh Market Chowk, Fuwara, Town Hall, Amritsar | F8323: Town Hall | G8323: Town Hall, Amritsar | H8323: 74.879814 | I8323: 31.624047 | J8323: North Indian, South Indian, Chinese, Fast Food | K8323: Indian Rupees(Rs.) | L8323: No | M8323: No | N8323: No | O8323: No | P8323: 2 | Q8323: 44 | R8323: 600 | S8323: =IF(Table1[[#This Row],[Average_Cost_for_two]]<500,"Low",IF(Table1[[#This Row],[Average_Cost_for_two]]<=1500,"Medium","High")) -> Medium | T8323: 3.4 | U8323: 2010 | V8323: 3 | W8323: 3 | X8323: =IF(OR(Main!$U8323=0, Main!$V8323=0, Main!$W8323=0), "", DATE(Main!$U8323, Main!$V8323, Main!$W8323) ) -> 40240 | Y8323: =Table1[[#This Row],[Average_Cost_for_two]]*VLOOKUP(Table1[[#This Row],[Currency]],currency!$A$2:$B$10,2,FALSE) -> 7.2 | Z8323: =VLOOKUP(C8323,country!A:B,2,FALSE) -> India | AA8323: =ROUNDUP(V8323/3,0) -> 1
A8324: 3400325 | B8324: MoMo Cafe | C8324: 1 | D8324: Agra | E8324: Courtyard by Marriott Agra, Phase 2, Fatehabad Road, Tajganj, Agra | F8324: Courtyard by Marriott Agra, Tajganj | G8324: Courtyard by Marriott Agra, Tajganj, Agra | H8324: 0 | I8324: 0 | J8324: North Indian, European | K8324: Indian Rupees(Rs.) | L8324: No | M8324: No | N8324: No | O8324: No | P8324: 4 | Q8324: 45 | R8324: 2000 | S8324: =IF(Table1[[#This Row],[Average_Cost_for_two]]<500,"Low",IF(Table1[[#This Row],[Average_Cost_for_two]]<=1500,"Medium","High")) -> High | T8324: 4 | U8324: 2018 | V8324: 9 | W8324: 24 | X8324: =IF(OR(Main!$U8324=0, Main!$V8324=0, Main!$W8324=0), "", DATE(Main!$U8324, Main!$V8324, Main!$W8324) ) -> 43367 | Y8324: =Table1[[#This Row],[Average_Cost_for_two]]*VLOOKUP(Table1[[#This Row],[Currency]],currency!$A$2:$B$10,2,FALSE) -> 24 | Z8324: =VLOOKUP(C8324,country!A:B,2,FALSE) -> India | AA8324: =ROUNDUP(V8324/3,0) -> 3
A8325: 18022206 | B8325: Antares | C8325: 1 | D8325: Goa | E8325: Small Vagator Beach, Ozran, Vagator, Goa | F8325: Vagator | G8325: Vagator, Goa | H8325: 0 | I8325: 0 | J8325: Seafood | K8325: Indian Rupees(Rs.) | L8325: No | M8325: No | N8325: No | O8325: No | P8325: 4 | Q8325: 367 | R8325: 2000 | S8325: =IF(Table1[[#This Row],[Average_Cost_for_two]]<500,"Low",IF(Table1[[#This Row],[Average_Cost_for_two]]<=1500,"Medium","High")) -> High | T8325: 4.2 | U8325: 2011 | V8325: 11 | W8325: 26 | X8325: =IF(OR(Main!$U8325=0, Main!$V8325=0, Main!$W8325=0), "", DATE(Main!$U8325, Main!$V8325, Main!$W8325) ) -> 40873 | Y8325: =Table1[[#This Row],[Average_Cost_for_two]]*VLOOKUP(Table1[[#This Row],[Currency]],currency!$A$2:$B$10,2,FALSE) -> 24 | Z8325: =VLOOKUP(C8325,country!A:B,2,FALSE) -> India | AA8325: =ROUNDUP(V8325/3,0) -> 4
A8326: 18339874 | B8326: Farzi Cafe | C8326: 1 | D8326: Bangalore | E8326: 202, Level 2, UB City, Vittal Mallya Road, Lavelle Road, Bangalore | F8326: UB City | G8326: UB City, Bangalore | H8326: 77.596014 | I8326: 12.972161 | J8326: Modern Indian | K8326: Indian Rupees(Rs.) | L8326: No | M8326: No | N8326: No | O8326: No | P8326: 3 | Q8326: 754 | R8326: 1500 | S8326: =IF(Table1[[#This Row],[Average_Cost_for_two]]<500,"Low",IF(Table1[[#This Row],[Average_Cost_for_two]]<=1500,"Medium","High")) -> Medium | T8326: 4.4 | U8326: 2010 | V8326: 3 | W8326: 5 | X8326: =IF(OR(Main!$U8326=0, Main!$V8326=0, Main!$W8326=0), "", DATE(Main!$U8326, Main!$V8326, Main!$W8326) ) -> 40242 | Y8326: =Table1[[#This Row],[Average_Cost_for_two]]*VLOOKUP(Table1[[#This Row],[Currency]],currency!$A$2:$B$10,2,FALSE) -> 18 | Z8326: =VLOOKUP(C8326,country!A:B,2,FALSE) -> India | AA8326: =ROUNDUP(V8326/3,0) -> 1
A8327: 18408676 | B8327: Central Perk 7 | C8327: 1 | D8327: Bhubaneshwar | E8327: Plot 133/A, District Center, Chandrasekharpur, Bhubaneshwar | F8327: Chandrasekharpur | G8327: Chandrasekharpur, Bhubaneshwar | H8327: 85.817813 | I8327: 20.325539 | J8327: Cafe, Charcoal Grill, Steak | K8327: Indian Rupees(Rs.) | L8327: No | M8327: No | N8327: No | O8327: No | P8327: 2 | Q8327: 145 | R8327: 600 | S8327: =IF(Table1[[#This Row],[Average_Cost_for_two]]<500,"Low",IF(Table1[[#This Row],[Average_Cost_for_two]]<=1500,"Medium","High")) -> Medium | T8327: 4.5 | U8327: 2015 | V8327: 3 | W8327: 11 | X8327: =IF(OR(Main!$U8327=0, Main!$V8327=0, Main!$W8327=0), "", DATE(Main!$U8327, Main!$V8327, Main!$W8327) ) -> 42074 | Y8327: =Table1[[#This Row],[Average_Cost_for_two]]*VLOOKUP(Table1[[#This Row],[Currency]],currency!$A$2:$B$10,2,FALSE) -> 7.2 | Z8327: =VLOOKUP(C8327,country!A:B,2,FALSE) -> India | AA8327: =ROUNDUP(V8327/3,0) -> 1
A8328: 2900234 | B8328: The Chicken Dinesty | C8328: 1 | D8328: Bhubaneshwar | E8328: District Center, Niladri Vihar Road, Chandrasekharpur, Bhubaneshwar | F8328: Chandrasekharpur | G8328: Chandrasekharpur, Bhubaneshwar | H8328: 85.818567 | I8328: 20.326344 | J8328: Fast Food, North Indian, Chinese | K8328: Indian Rupees(Rs.) | L8328: No | M8328: No | N8328: No | O8328: No | P8328: 2 | Q8328: 247 | R8328: 500 | S8328: =IF(Table1[[#This Row],[Average_Cost_for_two]]<500,"Low",IF(Table1[[#This Row],[Average_Cost_for_two]]<=1500,"Medium","High")) -> Medium | T8328: 3.9 | U8328: 2011 | V8328: 3 | W8328: 26 | X8328: =IF(OR(Main!$U8328=0, Main!$V8328=0, Main!$W8328=0), "", DATE(Main!$U8328, Main!$V8328, Main!$W8328) ) -> 40628 | Y8328: =Table1[[#This Row],[Average_Cost_for_two]]*VLOOKUP(Table1[[#This Row],[Currency]],currency!$A$2:$B$10,2,FALSE) -> 6 | Z8328: =VLOOKUP(C8328,country!A:B,2,FALSE) -> India | AA8328: =ROUNDUP(V8328/3,0) -> 1
A8329: 18436042 | B8329: Eram Rooftop | C8329: 1 | D8329: Bhubaneshwar | E8329: 206, 3rd Floor, Suryansh Enclave, Shastri Nagar, Unit 4, Bhubaneshwar | F8329: Unit 4 | G8329: Unit 4, Bhubaneshwar | H8329: 85.826696 | I8329: 20.283989 | J8329: Asian, Continental | K8329: Indian Rupees(Rs.) | L8329: No | M8329: No | N8329: No | O8329: No | P8329: 1 | Q8329: 89 | R8329: 400 | S8329: =IF(Table1[[#This Row],[Average_Cost_for_two]]<500,"Low",IF(Table1[[#This Row],[Average_Cost_for_two]]<=1500,"Medium","High")) -> Low | T8329: 3.5 | U8329: 2018 | V8329: 3 | W8329: 5 | X8329: =IF(OR(Main!$U8329=0, Main!$V8329=0, Main!$W8329=0), "", DATE(Main!$U8329, Main!$V8329, Main!$W8329) ) -> 43164 | Y8329: =Table1[[#This Row],[Average_Cost_for_two]]*VLOOKUP(Table1[[#This Row],[Currency]],currency!$A$2:$B$10,2,FALSE) -> 4.8 | Z8329: =VLOOKUP(C8329,country!A:B,2,FALSE) -> India | AA8329: =ROUNDUP(V8329/3,0) -> 1
A8330: 71492 | B8330: Ciclo Cafe | C8330: 1 | D8330: Chennai | E8330: 47, Gandhi Mandapam Road, Kotturpuram, Chennai | F8330: Kotturpuram | G8330: Kotturpuram, Chennai | H8330: 80.242439 | I8330: 13.022394 | J8330: Cafe, Continental | K8330: Indian Rupees(Rs.) | L8330: No | M8330: No | N8330: No | O8330: No | P8330: 3 | Q8330: 1004 | R8330: 1100 | S8330: =IF(Table1[[#This Row],[Average_Cost_for_two]]<500,"Low",IF(Table1[[#This Row],[Average_Cost_for_two]]<=1500,"Medium","High")) -> Medium | T8330: 4.1 | U8330: 2018 | V8330: 3 | W8330: 21 | X8330: =IF(OR(Main!$U8330=0, Main!$V8330=0, Main!$W8330=0), "", DATE(Main!$U8330, Main!$V8330, Main!$W8330) ) -> 43180 | Y8330: =Table1[[#This Row],[Average_Cost_for_two]]*VLOOKUP(Table1[[#This Row],[Currency]],currency!$A$2:$B$10,2,FALSE) -> 13.2 | Z8330: =VLOOKUP(C8330,country!A:B,2,FALSE) -> India | AA8330: =ROUNDUP(V8330/3,0) -> 1
A8331: 18434000 | B8331: 24 Plus Cafe & Restaurant | C8331: 1 | D8331: Coimbatore | E8331: 1A, Pollachi Main Road, Eachanari, Podanur, Coimbatore | F8331: Podanur | G8331: Podanur, Coimbatore | H8331: 76.971082 | I8331: 10.96185 | J8331: Continental, Fast Food, Desserts, Indian | K8331: Indian Rupees(Rs.) | L8331: No | M8331: No | N8331: No | O8331: No | P8331: 2 | Q8331: 24 | R8331: 450 | S8331: =IF(Table1[[#This Row],[Average_Cost_for_two]]<500,"Low",IF(Table1[[#This Row],[Average_Cost_for_two]]<=1500,"Medium","High")) -> Low | T8331: 3.8 | U8331: 2013 | V8331: 3 | W8331: 28 | X8331: =IF(OR(Main!$U8331=0, Main!$V8331=0, Main!$W8331=0), "", DATE(Main!$U8331, Main!$V8331, Main!$W8331) ) -> 41361 | Y8331: =Table1[[#This Row],[Average_Cost_for_two]]*VLOOKUP(Table1[[#This Row],[Currency]],currency!$A$2:$B$10,2,FALSE) -> 5.4 | Z8331: =VLOOKUP(C8331,country!A:B,2,FALSE) -> India | AA8331: =ROUNDUP(V8331/3,0) -> 1
A8332: 3000126 | B8332: Bird On Tree | C8332: 1 | D8332: Coimbatore | E8332: 28, Opposite Circuit House, Behind HDFC, Race Course, Coimbatore | F8332: Race Course | G8332: Race Course, Coimbatore | H8332: 76.984311 | I8332: 11.008638 | J8332: Continental, Chinese, Thai, Malaysian, North Indian | K8332: Indian Rupees(Rs.) | L8332: No | M8332: No | N8332: No | O8332: No | P8332: 3 | Q8332: 221 | R8332: 1200 | S8332: =IF(Table1[[#This Row],[Average_Cost_for_two]]<500,"Low",IF(Table1[[#This Row],[Average_Cost_for_two]]<=1500,"Medium","High")) -> Medium | T8332: 3.8 | U8332: 2013 | V8332: 3 | W8332: 2 | X8332: =IF(OR(Main!$U8332=0, Main!$V8332=0, Main!$W8332=0), "", DATE(Main!$U8332, Main!$V8332, Main!$W8332) ) -> 41335 | Y8332: =Table1[[#This Row],[Average_Cost_for_two]]*VLOOKUP(Table1[[#This Row],[Currency]],currency!$A$2:$B$10,2,FALSE) -> 14.4 | Z8332: =VLOOKUP(C8332,country!A:B,2,FALSE) -> India | AA8332: =ROUNDUP(V8332/3,0) -> 1
... A8442: 3900009 | B8442: eastWEST - Radisson Hotel | C8442: 1 | D8442: Varanasi | E8442: Radisson Hotel, The Mall Road, Nadesar, Varanasi | F8442: Radisson Hotel, Nadesar | G8442: Radisson Hotel, Nadesar, Varanasi | H8442: 82.98081 | I8442: 25.338373 | J8442: Cafe, North Indian, Continental | K8442: Indian Rupees(Rs.) | L8442: No | M8442: No | N8442: No | O8442: No | P8442: 3 | Q8442: 34 | R8442: 600 | S8442: =IF(Table1[[#This Row],[Average_Cost_for_two]]<500,"Low",IF(Table1[[#This Row],[Average_Cost_for_two]]<=1500,"Medium","High")) -> Medium | T8442: 3.3 | U8442: 2018 | V8442: 1 | W8442: 19 | X8442: =IF(OR(Main!$U8442=0, Main!$V8442=0, Main!$W8442=0), "", DATE(Main!$U8442, Main!$V8442, Main!$W8442) ) -> 43119 | Y8442: =Table1[[#This Row],[Average_Cost_for_two]]*VLOOKUP(Table1[[#This Row],[Currency]],currency!$A$2:$B$10,2,FALSE) -> 7.2 | Z8442: =VLOOKUP(C8442,country!A:B,2,FALSE) -> India | AA8442: =ROUNDUP(V8442/3,0) -> 1
A8443: 18246202 | B8443: VNS Live Studio | C8443: 1 | D8443: Varanasi | E8443: Hotel Varuna Ground Floor, 22 Gulab Bagh, Sigra, Varanasi | F8443: Sigra | G8443: Sigra, Varanasi | H8443: 82.991694 | I8443: 25.318345 | J8443: Chinese, North Indian | K8443: Indian Rupees(Rs.) | L8443: No | M8443: No | N8443: No | O8443: No | P8443: 1 | Q8443: 109 | S8443: =IF(Table1[[#This Row],[Average_Cost_for_two]]<500,"Low",IF(Table1[[#This Row],[Average_Cost_for_two]]<=1500,"Medium","High")) -> Low | T8443: 3.5 | U8443: 2012 | V8443: 1 | W8443: 22 | X8443: =IF(OR(Main!$U8443=0, Main!$V8443=0, Main!$W8443=0), "", DATE(Main!$U8443, Main!$V8443, Main!$W8443) ) -> 40930 | Y8443: =Table1[[#This Row],[Average_Cost_for_two]]*VLOOKUP(Table1[[#This Row],[Currency]],currency!$A$2:$B$10,2,FALSE) -> 0 | Z8443: =VLOOKUP(C8443,country!A:B,2,FALSE) -> India | AA8443: =ROUNDUP(V8443/3,0) -> 1
A8444: 2800013 | B8444: Pizza Hut | C8444: 1 | D8444: Vizag | E8444: 52-1-35,36&38, CMR Mall, New Resapavanipalem, Maddilapalem, Vizag | F8444: CMR Central Mall, Maddilapalem | G8444: CMR Central Mall, Maddilapalem, Vizag | H8444: 83.318511 | I8444: 17.734178 | J8444: Pizza, Fast Food | K8444: Indian Rupees(Rs.) | L8444: No | M8444: No | N8444: No | O8444: No | P8444: 2 | Q8444: 289 | R8444: 600 | S8444: =IF(Table1[[#This Row],[Average_Cost_for_two]]<500,"Low",IF(Table1[[#This Row],[Average_Cost_for_two]]<=1500,"Medium","High")) -> Medium | T8444: 4.6 | U8444: 2017 | V8444: 1 | W8444: 25 | X8444: =IF(OR(Main!$U8444=0, Main!$V8444=0, Main!$W8444=0), "", DATE(Main!$U8444, Main!$V8444, Main!$W8444) ) -> 42760 | Y8444: =Table1[[#This Row],[Average_Cost_for_two]]*VLOOKUP(Table1[[#This Row],[Currency]],currency!$A$2:$B$10,2,FALSE) -> 7.2 | Z8444: =VLOOKUP(C8444,country!A:B,2,FALSE) -> India | AA8444: =ROUNDUP(V8444/3,0) -> 1
A8445: 18408040 | B8445: Lord of the Drinks Meadow | C8445: 1 | D8445: New Delhi | E8445: Inside Deer Park, Hauz Khas Village, New Delhi | F8445: Hauz Khas Village | G8445: Hauz Khas Village, New Delhi | H8445: 77.195274 | I8445: 28.555748 | J8445: European, Chinese, North Indian, Italian | K8445: Indian Rupees(Rs.) | L8445: Yes | M8445: No | N8445: No | O8445: No | P8445: 4 | Q8445: 278 | R8445: 2200 | S8445: =IF(Table1[[#This Row],[Average_Cost_for_two]]<500,"Low",IF(Table1[[#This Row],[Average_Cost_for_two]]<=1500,"Medium","High")) -> High | T8445: 4.2 | U8445: 2010 | V8445: 9 | W8445: 7 | X8445: =IF(OR(Main!$U8445=0, Main!$V8445=0, Main!$W8445=0), "", DATE(Main!$U8445, Main!$V8445, Main!$W8445) ) -> 40428 | Y8445: =Table1[[#This Row],[Average_Cost_for_two]]*VLOOKUP(Table1[[#This Row],[Currency]],currency!$A$2:$B$10,2,FALSE) -> 26.4 | Z8445: =VLOOKUP(C8445,country!A:B,2,FALSE) -> India | AA8445: =ROUNDUP(V8445/3,0) -> 3
A8446: 3400025 | B8446: Jahanpanah | C8446: 1 | D8446: Agra | E8446: E 23, Shopping Arcade, Sadar Bazaar, Agra Cantt, Agra | F8446: Agra Cantt | G8446: Agra Cantt, Agra | H8446: 78.011544 | I8446: 27.161661 | J8446: North Indian, Mughlai | K8446: Indian Rupees(Rs.) | L8446: No | M8446: No | N8446: No | O8446: No | P8446: 3 | Q8446: 140 | R8446: 850 | S8446: =IF(Table1[[#This Row],[Average_Cost_for_two]]<500,"Low",IF(Table1[[#This Row],[Average_Cost_for_two]]<=1500,"Medium","High")) -> Medium | T8446: 3.9 | U8446: 2018 | V8446: 12 | W8446: 11 | X8446: =IF(OR(Main!$U8446=0, Main!$V8446=0, Main!$W8446=0), "", DATE(Main!$U8446, Main!$V8446, Main!$W8446) ) -> 43445 | Y8446: =Table1[[#This Row],[Average_Cost_for_two]]*VLOOKUP(Table1[[#This Row],[Currency]],currency!$A$2:$B$10,2,FALSE) -> 10.2 | Z8446: =VLOOKUP(C8446,country!A:B,2,FALSE) -> India | AA8446: =ROUNDUP(V8446/3,0) -> 4
A8447: 3400019 | B8447: Dasaprakash Restaurant | C8447: 1 | D8447: Agra | E8447: Meher Cinema Complex, Gwalior Road, Rakabganj, Agra | F8447: Rakabganj | G8447: Rakabganj, Agra | H8447: 78.015053 | I8447: 27.165108 | J8447: South Indian, Desserts | K8447: Indian Rupees(Rs.) | L8447: No | M8447: No | N8447: No | O8447: No | P8447: 2 | Q8447: 121 | R8447: 550 | S8447: =IF(Table1[[#This Row],[Average_Cost_for_two]]<500,"Low",IF(Table1[[#This Row],[Average_Cost_for_two]]<=1500,"Medium","High")) -> Medium | T8447: 4.1 | U8447: 2018 | V8447: 12 | W8447: 7 | X8447: =IF(OR(Main!$U8447=0, Main!$V8447=0, Main!$W8447=0), "", DATE(Main!$U8447, Main!$V8447, Main!$W8447) ) -> 43441 | Y8447: =Table1[[#This Row],[Average_Cost_for_two]]*VLOOKUP(Table1[[#This Row],[Currency]],currency!$A$2:$B$10,2,FALSE) -> 6.6 | Z8447: =VLOOKUP(C8447,country!A:B,2,FALSE) -> India | AA8447: =ROUNDUP(V8447/3,0) -> 4
A8448: 2400027 | B8448: Friends Forever | C8448: 1 | D8448: Allahabad | E8448: 13/13, Sardar Patel Marg, Civil Lines, Allahabad | F8448: Civil Lines | G8448: Civil Lines, Allahabad | H8448: 81.835585 | I8448: 25.457687 | J8448: North Indian, Chinese | K8448: Indian Rupees(Rs.) | L8448: No | M8448: No | N8448: No | O8448: No | P8448: 3 | Q8448: 83 | R8448: 600 | S8448: =IF(Table1[[#This Row],[Average_Cost_for_two]]<500,"Low",IF(Table1[[#This Row],[Average_Cost_for_two]]<=1500,"Medium","High")) -> Medium | T8448: 3.4 | U8448: 2015 | V8448: 12 | W8448: 20 | X8448: =IF(OR(Main!$U8448=0, Main!$V8448=0, Main!$W8448=0), "", DATE(Main!$U8448, Main!$V8448, Main!$W8448) ) -> 42358 | Y8448: =Table1[[#This Row],[Average_Cost_for_two]]*VLOOKUP(Table1[[#This Row],[Currency]],currency!$A$2:$B$10,2,FALSE) -> 7.2 | Z8448: =VLOOKUP(C8448,country!A:B,2,FALSE) -> India | AA8448: =ROUNDUP(V8448/3,0) -> 4
A8449: 2200011 | B8449: Makhan Fish and Chicken Corner | C8449: 1 | D8449: Amritsar | E8449: 21-A, Near Madaan Hospital, Majitha Road, Basant Nagar, Amritsar | F8449: Basant Nagar | G8449: Basant Nagar, Amritsar | H8449: 74.884359 | I8449: 31.64362 | J8449: North Indian, Chinese | K8449: Indian Rupees(Rs.) | L8449: No | M8449: No | N8449: No | O8449: No | P8449: 2 | Q8449: 345 | R8449: 700 | S8449: =IF(Table1[[#This Row],[Average_Cost_for_two]]<500,"Low",IF(Table1[[#This Row],[Average_Cost_for_two]]<=1500,"Medium","High")) -> Medium | T8449: 3.4 | U8449: 2013 | V8449: 12 | W8449: 5 | X8449: =IF(OR(Main!$U8449=0, Main!$V8449=0, Main!$W8449=0), "", DATE(Main!$U8449, Main!$V8449, Main!$W8449) ) -> 41613 | Y8449: =Table1[[#This Row],[Average_Cost_for_two]]*VLOOKUP(Table1[[#This Row],[Currency]],currency!$A$2:$B$10,2,FALSE) -> 8.4 | Z8449: =VLOOKUP(C8449,country!A:B,2,FALSE) -> India | AA8449: =ROUNDUP(V8449/3,0) -> 4
A8450: 2200078 | B8450: Charming Chicken | C8450: 1 | D8450: Amritsar | E8450: Shop 3, Opposite Nari Nikaten, Majithia Road, Near Basant Nagar, Amritsar | F8450: Basant Nagar | G8450: Basant Nagar, Amritsar | H8450: 74.884384 | I8450: 31.644532 | J8450: North Indian | K8450: Indian Rupees(Rs.) | L8450: No | M8450: No | N8450: No | O8450: No | P8450: 1 | Q8450: 151 | R8450: 300 | S8450: =IF(Table1[[#This Row],[Average_Cost_for_two]]<500,"Low",IF(Table1[[#This Row],[Average_Cost_for_two]]<=1500,"Medium","High")) -> Low | T8450: 3.9 | U8450: 2015 | V8450: 12 | W8450: 23 | X8450: =IF(OR(Main!$U8450=0, Main!$V8450=0, Main!$W8450=0), "", DATE(Main!$U8450, Main!$V8450, Main!$W8450) ) -> 42361 | Y8450: =Table1[[#This Row],[Average_Cost_for_two]]*VLOOKUP(Table1[[#This Row],[Currency]],currency!$A$2:$B$10,2,FALSE) -> 3.6 | Z8450: =VLOOKUP(C8450,country!A:B,2,FALSE) -> India | AA8450: =ROUNDUP(V8450/3,0) -> 4
A8451: 2500052 | B8451: Ashoka's Veg Restaurant | C8451: 1 | D8451: Aurangabad | E8451: 31, Opposite Kohinoor Plaza, Near M P Law College, Nirala Bazar, Aurangabad | F8451: Nirala Bazar | G8451: Nirala Bazar, Aurangabad | H8451: 75.323403 | I8451: 19.879631 | J8451: South Indian, Chinese, North Indian | K8451: Indian Rupees(Rs.) | L8451: No | M8451: No | N8451: No | O8451: No | P8451: 2 | Q8451: 46 | R8451: 400 | S8451: =IF(Table1[[#This Row],[Average_Cost_for_two]]<500,"Low",IF(Table1[[#This Row],[Average_Cost_for_two]]<=1500,"Medium","High")) -> Low | T8451: 3.3 | U8451: 2013 | V8451: 12 | W8451: 8 | X8451: =IF(OR(Main!$U8451=0, Main!$V8451=0, Main!$W8451=0), "", DATE(Main!$U8451, Main!$V8451, Main!$W8451) ) -> 41616 | Y8451: =Table1[[#This Row],[Average_Cost_for_two]]*VLOOKUP(Table1[[#This Row],[Currency]],currency!$A$2:$B$10,2,FALSE) -> 4.8 | Z8451: =VLOOKUP(C8451,country!A:B,2,FALSE) -> India | AA8451: =ROUNDUP(V8451/3,0) -> 4
A8452: 2600031 | B8452: 10 Downing Street | C8452: 1 | D8452: Bhopal | E8452: Third Floor, DB City Mall, Maharana Pratap Nagar, Bhopal | F8452: DB City, Maharana Pratap Nagar | G8452: DB City, Maharana Pratap Nagar, Bhopal | H8452: 77.429989 | I8452: 23.232357 | J8452: North Indian, Chinese | K8452: Indian Rupees(Rs.) | L8452: No | M8452: No | N8452: No | O8452: No | P8452: 3 | Q8452: 257 | R8452: 1000 | S8452: =IF(Table1[[#This Row],[Average_Cost_for_two]]<500,"Low",IF(Table1[[#This Row],[Average_Cost_for_two]]<=1500,"Medium","High")) -> Medium | T8452: 4 | U8452: 2015 | V8452: 12 | W8452: 22 | X8452: =IF(OR(Main!$U8452=0, Main!$V8452=0, Main!$W8452=0), "", DATE(Main!$U8452, Main!$V8452, Main!$W8452) ) -> 42360 | Y8452: =Table1[[#This Row],[Average_Cost_for_two]]*VLOOKUP(Table1[[#This Row],[Currency]],currency!$A$2:$B$10,2,FALSE) -> 12 | Z8452: =VLOOKUP(C8452,country!A:B,2,FALSE) -> India | AA8452: =ROUNDUP(V8452/3,0) -> 4
A8453: 121552 | B8453: Brooklyn Central | C8453: 1 | D8453: Chandigarh | E8453: Courtyard, Elante Mall, Phase 1, Chandigarh Industrial Area, Chandigarh | F8453: Elante Mall, Chandigarh Industrial Area | G8453: Elante Mall, Chandigarh Industrial Area, Chandigarh | H8453: 76.800956 | I8453: 30.705069 | J8453: American, Cafe | K8453: Indian Rupees(Rs.) | L8453: No | M8453: No | N8453: No | O8453: No | P8453: 3 | Q8453: 676 | R8453: 1600 | S8453: =IF(Table1[[#This Row],[Average_Cost_for_two]]<500,"Low",IF(Table1[[#This Row],[Average_Cost_for_two]]<=1500,"Medium","High")) -> High | T8453: 4.2 | U8453: 2014 | V8453: 12 | W8453: 2 | X8453: =IF(OR(Main!$U8453=0, Main!$V8453=0, Main!$W8453=0), "", DATE(Main!$U8453, Main!$V8453, Main!$W8453) ) -> 41975 | Y8453: =Table1[[#This Row],[Average_Cost_for_two]]*VLOOKUP(Table1[[#This Row],[Currency]],currency!$A$2:$B$10,2,FALSE) -> 19.2 | Z8453: =VLOOKUP(C8453,country!A:B,2,FALSE) -> India | AA8453: =ROUNDUP(V8453/3,0) -> 4
A8454: 123294 | B8454: Karim's | C8454: 1 | D8454: Chandigarh | E8454: SCO 33, Madhya Marg, Sector 7, Chandigarh | F8454: Sector 7 | G8454: Sector 7, Chandigarh | H8454: 76.800979 | I8454: 30.730618 | J8454: Mughlai, North Indian | K8454: Indian Rupees(Rs.) | L8454: No | M8454: No | N8454: No | O8454: No | P8454: 2 | Q8454: 86 | R8454: 800 | S8454: =IF(Table1[[#This Row],[Average_Cost_for_two]]<500,"Low",IF(Table1[[#This Row],[Average_Cost_for_two]]<=1500,"Medium","High")) -> Medium | T8454: 3.3 | U8454: 2013 | V8454: 12 | W8454: 25 | X8454: =IF(OR(Main!$U8454=0, Main!$V8454=0, Main!$W8454=0), "", DATE(Main!$U8454, Main!$V8454, Main!$W8454) ) -> 41633 | Y8454: =Table1[[#This Row],[Average_Cost_for_two]]*VLOOKUP(Table1[[#This Row],[Currency]],currency!$A$2:$B$10,2,FALSE) -> 9.6 | Z8454: =VLOOKUP(C8454,country!A:B,2,FALSE) -> India | AA8454: =ROUNDUP(V8454/3,0) -> 4
A8455: 18279289 | B8455: BMG - All Day Dining | C8455: 1 | D8455: Dehradun | E8455: 140 A, Rajpur Road, Jakhan, Dehradun | F8455: Jakhan | G8455: Jakhan, Dehradun | H8455: 78.06889 | I8455: 30.362686 | J8455: Chinese, North Indian, Fast Food | K8455: Indian Rupees(Rs.) | L8455: No | M8455: No | N8455: No | O8455: No | P8455: 1 | Q8455: 63 | S8455: =IF(Table1[[#This Row],[Average_Cost_for_two]]<500,"Low",IF(Table1[[#This Row],[Average_Cost_for_two]]<=1500,"Medium","High")) -> Low | T8455: 4.3 | U8455: 2013 | V8455: 12 | W8455: 25 | X8455: =IF(OR(Main!$U8455=0, Main!$V8455=0, Main!$W8455=0), "", DATE(Main!$U8455, Main!$V8455, Main!$W8455) ) -> 41633 | Y8455: =Table1[[#This Row],[Average_Cost_for_two]]*VLOOKUP(Table1[[#This Row],[Currency]],currency!$A$2:$B$10,2,FALSE) -> 0 | Z8455: =VLOOKUP(C8455,country!A:B,2,FALSE) -> India | AA8455: =ROUNDUP(V8455/3,0) -> 4
A8456: 3500024 | B8456: Doon Darbar | C8456: 1 | D8456: Dehradun | E8456: 43, Gandhi Road, Paltan Bazaar, Dehradun | F8456: Paltan Bazaar | G8456: Paltan Bazaar, Dehradun | H8456: 78.040267 | I8456: 30.319528 | J8456: North Indian, Mughlai | K8456: Indian Rupees(Rs.) | L8456: No | M8456: No | N8456: No | O8456: No | P8456: 3 | Q8456: 121 | R8456: 600 | S8456: =IF(Table1[[#This Row],[Average_Cost_for_two]]<500,"Low",IF(Table1[[#This Row],[Average_Cost_for_two]]<=1500,"Medium","High")) -> Medium | T8456: 3.9 | U8456: 2012 | V8456: 12 | W8456: 5 | X8456: =IF(OR(Main!$U8456=0, Main!$V8456=0, Main!$W8456=0), "", DATE(Main!$U8456, Main!$V8456, Main!$W8456) ) -> 41248 | Y8456: =Table1[[#This Row],[Average_Cost_for_two]]*VLOOKUP(Table1[[#This Row],[Currency]],currency!$A$2:$B$10,2,FALSE) -> 7.2 | Z8456: =VLOOKUP(C8456,country!A:B,2,FALSE) -> India | AA8456: =ROUNDUP(V8456/3,0) -> 4
A8457: 307903 | B8457: Thakur Bakers | C8457: 1 | D8457: Ghaziabad | E8457: Shop 24, Regalia Heights, Shipra Suncity, Indirapuram, Ghaziabad | F8457: Indirapuram | G8457: Indirapuram, Ghaziabad | H8457: 77.374192 | I8457: 28.636022 | J8457: Bakery | K8457: Indian Rupees(Rs.) | L8457: No | M8457: No | N8457: No | O8457: No | P8457: 1 | Q8457: 6 | R8457: 150 | S8457: =IF(Table1[[#This Row],[Average_Cost_for_two]]<500,"Low",IF(Table1[[#This Row],[Average_Cost_for_two]]<=1500,"Medium","High")) -> Low | T8457: 3 | U8457: 2014 | V8457: 12 | W8457: 14 | X8457: =IF(OR(Main!$U8457=0, Main!$V8457=0, Main!$W8457=0), "", DATE(Main!$U8457, Main!$V8457, Main!$W8457) ) -> 41987 | Y8457: =Table1[[#This Row],[Average_Cost_for_two]]*VLOOKUP(Table1[[#This Row],[Currency]],currency!$A$2:$B$10,2,FALSE) -> 1.8 | Z8457: =VLOOKUP(C8457,country!A:B,2,FALSE) -> India | AA8457: =ROUNDUP(V8457/3,0) -> 4
A8458: 8583 | B8458: Chinese X'Press | C8458: 1 | D8458: Ghaziabad | E8458: Bite Inn Food Court, 2nd Floor, Shipra Mall, Gulmohar Road, Indirapuram, Ghaziabad | F8458: Shipra Mall, Indirapuram | G8458: Shipra Mall, Indirapuram, Ghaziabad | H8458: 77.369865 | I8458: 28.633883 | J8458: Chinese | K8458: Indian Rupees(Rs.) | L8458: No | M8458: No | N8458: No | O8458: No | P8458: 2 | Q8458: 16 | R8458: 600 | S8458: =IF(Table1[[#This Row],[Average_Cost_for_two]]<500,"Low",IF(Table1[[#This Row],[Average_Cost_for_two]]<=1500,"Medium","High")) -> Medium | T8458: 2.9 | U8458: 2014 | V8458: 12 | W8458: 11 | X8458: =IF(OR(Main!$U8458=0, Main!$V8458=0, Main!$W8458=0), "", DATE(Main!$U8458, Main!$V8458, Main!$W8458) ) -> 41984 | Y8458: =Table1[[#This Row],[Average_Cost_for_two]]*VLOOKUP(Table1[[#This Row],[Currency]],currency!$A$2:$B$10,2,FALSE) -> 7.2 | Z8458: =VLOOKUP(C8458,country!A:B,2,FALSE) -> India | AA8458: =ROUNDUP(V8458/3,0) -> 4
A8459: 18381223 | B8459: Dosa X'press | C8459: 1 | D8459: Ghaziabad | E8459: Food Court, 2nd Floor, Shipra Mall, Indirapuram, Ghaziabad | F8459: Shipra Mall, Indirapuram | G8459: Shipra Mall, Indirapuram, Ghaziabad | H8459: 77.369728 | I8459: 28.633788 | J8459: South Indian | K8459: Indian Rupees(Rs.) | L8459: No | M8459: No | N8459: No | O8459: No | P8459: 2 | Q8459: 6 | R8459: 500 | S8459: =IF(Table1[[#This Row],[Average_Cost_for_two]]<500,"Low",IF(Table1[[#This Row],[Average_Cost_for_two]]<=1500,"Medium","High")) -> Medium | T8459: 3 | U8459: 2014 | V8459: 12 | W8459: 5 | X8459: =IF(OR(Main!$U8459=0, Main!$V8459=0, Main!$W8459=0), "", DATE(Main!$U8459, Main!$V8459, Main!$W8459) ) -> 41978 | Y8459: =Table1[[#This Row],[Average_Cost_for_two]]*VLOOKUP(Table1[[#This Row],[Currency]],currency!$A$2:$B$10,2,FALSE) -> 6 | Z8459: =VLOOKUP(C8459,country!A:B,2,FALSE) -> India | AA8459: =ROUNDUP(V8459/3,0) -> 4
A8460: 18264963 | B8460: Number 8 | C8460: 1 | D8460: New Delhi | E8460: 8, Sunder Nagar Market, Sunder Nagar, New Delhi | F8460: Sunder Nagar | G8460: Sunder Nagar, New Delhi | H8460: 77.241189 | I8460: 28.60247 | J8460: Continental, North Indian, European, Asian | K8460: Indian Rupees(Rs.) | L8460: No | M8460: No | N8460: No | O8460: No | P8460: 4 | Q8460: 165 | R8460: 2200 | S8460: =IF(Table1[[#This Row],[Average_Cost_for_two]]<500,"Low",IF(Table1[[#This Row],[Average_Cost_for_two]]<=1500,"Medium","High")) -> High | T8460: 4 | U8460: 2015 | V8460: 8 | W8460: 14 | X8460: =IF(OR(Main!$U8460=0, Main!$V8460=0, Main!$W8460=0), "", DATE(Main!$U8460, Main!$V8460, Main!$W8460) ) -> 42230 | Y8460: =Table1[[#This Row],[Average_Cost_for_two]]*VLOOKUP(Table1[[#This Row],[Currency]],currency!$A$2:$B$10,2,FALSE) -> 26.4 | Z8460: =VLOOKUP(C8460,country!A:B,2,FALSE) -> India | AA8460: =ROUNDUP(V8460/3,0) -> 3
A8461: 2100101 | B8461: Yo! China | C8461: 1 | D8461: Guwahati | E8461: 1st Floor, Adityam Building,Borthakur Mall Road, Ulubari, Guwahati | F8461: Ulubari | G8461: Ulubari, Guwahati | H8461: 91.758167 | I8461: 26.171 | J8461: Chinese | K8461: Indian Rupees(Rs.) | L8461: No | M8461: No | N8461: No | O8461: No | P8461: 3 | Q8461: 327 | R8461: 800 | S8461: =IF(Table1[[#This Row],[Average_Cost_for_two]]<500,"Low",IF(Table1[[#This Row],[Average_Cost_for_two]]<=1500,"Medium","High")) -> Medium | T8461: 3.6 | U8461: 2011 | V8461: 12 | W8461: 10 | X8461: =IF(OR(Main!$U8461=0, Main!$V8461=0, Main!$W8461=0), "", DATE(Main!$U8461, Main!$V8461, Main!$W8461) ) -> 40887 | Y8461: =Table1[[#This Row],[Average_Cost_for_two]]*VLOOKUP(Table1[[#This Row],[Currency]],currency!$A$2:$B$10,2,FALSE) -> 9.6 | Z8461: =VLOOKUP(C8461,country!A:B,2,FALSE) -> India | AA8461: =ROUNDUP(V8461/3,0) -> 4
A8462: 1401857 | B8462: The Yellow Chilli | C8462: 1 | D8462: Indore | E8462: Block B-3, Dhan Trident, Near Metro Tower, PU-4, Scheme 54, Vijay Nagar, Indore | F8462: Vijay Nagar | G8462: Vijay Nagar, Indore | H8462: 75.897429 | I8462: 22.753839 | J8462: North Indian, Mughlai, Seafood | K8462: Indian Rupees(Rs.) | L8462: No | M8462: No | N8462: No | O8462: No | P8462: 3 | Q8462: 181 | R8462: 1100 | S8462: =IF(Table1[[#This Row],[Average_Cost_for_two]]<500,"Low",IF(Table1[[#This Row],[Average_Cost_for_two]]<=1500,"Medium","High")) -> Medium | T8462: 4.1 | U8462: 2017 | V8462: 12 | W8462: 3 | X8462: =IF(OR(Main!$U8462=0, Main!$V8462=0, Main!$W8462=0), "", DATE(Main!$U8462, Main!$V8462, Main!$W8462) ) -> 43072 | Y8462: =Table1[[#This Row],[Average_Cost_for_two]]*VLOOKUP(Table1[[#This Row],[Currency]],currency!$A$2:$B$10,2,FALSE) -> 13.2 | Z8462: =VLOOKUP(C8462,country!A:B,2,FALSE) -> India | AA8462: =ROUNDUP(V8462/3,0) -> 4
A8463: 101834 | B8463: Blackout | C8463: 1 | D8463: Jaipur | E8463: Hotel Golden Oak, 9th Floor, Ahinsa Circle, Landmark Building, C Scheme, Jaipur | F8463: C Scheme | G8463: C Scheme, Jaipur | H8463: 75.805704 | I8463: 26.914142 | J8463: North Indian, European, Continental, Finger Food | K8463: Indian Rupees(Rs.) | L8463: No | M8463: No | N8463: No | O8463: No | P8463: 3 | Q8463: 676 | R8463: 1650 | S8463: =IF(Table1[[#This Row],[Average_Cost_for_two]]<500,"Low",IF(Table1[[#This Row],[Average_Cost_for_two]]<=1500,"Medium","High")) -> High | T8463: 3.9 | U8463: 2015 | V8463: 12 | W8463: 26 | X8463: =IF(OR(Main!$U8463=0, Main!$V8463=0, Main!$W8463=0), "", DATE(Main!$U8463, Main!$V8463, Main!$W8463) ) -> 42364 | Y8463: =Table1[[#This Row],[Average_Cost_for_two]]*VLOOKUP(Table1[[#This Row],[Currency]],currency!$A$2:$B$10,2,FALSE) -> 19.8 | Z8463: =VLOOKUP(C8463,country!A:B,2,FALSE) -> India | AA8463: =ROUNDUP(V8463/3,0) -> 4
A8464: 100306 | B8464: Replay | C8464: 1 | D8464: Jaipur | E8464: SB 57, 5th Floor, Ridhi Tower, Opposite SMS Stadium, Tonk Road, Jaipur | F8464: Tonk Road | G8464: Tonk Road, Jaipur | H8464: 75.806896 | I8464: 26.892312 | J8464: North Indian, Continental, Chinese, Italian, Mexican | K8464: Indian Rupees(Rs.) | L8464: No | M8464: No | N8464: No | O8464: No | P8464: 3 | Q8464: 1121 | R8464: 1500 | S8464: =IF(Table1[[#This Row],[Average_Cost_for_two]]<500,"Low",IF(Table1[[#This Row],[Average_Cost_for_two]]<=1500,"Medium","High")) -> Medium | T8464: 4.3 | U8464: 2013 | V8464: 12 | W8464: 1 | X8464: =IF(OR(Main!$U8464=0, Main!$V8464=0, Main!$W8464=0), "", DATE(Main!$U8464, Main!$V8464, Main!$W8464) ) -> 41609 | Y8464: =Table1[[#This Row],[Average_Cost_for_two]]*VLOOKUP(Table1[[#This Row],[Currency]],currency!$A$2:$B$10,2,FALSE) -> 18 | Z8464: =VLOOKUP(C8464,country!A:B,2,FALSE) -> India | AA8464: =ROUNDUP(V8464/3,0) -> 4
A8465: 2300476 | B8465: Dunkin Donuts | C8465: 1 | D8465: Kanpur | E8465: Third Floor, Plot 1 & 1A, Z Square Mall, Mall Road, Kanpur | F8465: Mall Road | G8465: Mall Road, Kanpur | H8465: 80.352677 | I8465: 26.473698 | J8465: Desserts, Fast Food | K8465: Indian Rupees(Rs.) | L8465: No | M8465: No | N8465: No | O8465: No | P8465: 2 | Q8465: 87 | R8465: 500 | S8465: =IF(Table1[[#This Row],[Average_Cost_for_two]]<500,"Low",IF(Table1[[#This Row],[Average_Cost_for_two]]<=1500,"Medium","High")) -> Medium | T8465: 4.1 | U8465: 2016 | V8465: 12 | W8465: 3 | X8465: =IF(OR(Main!$U8465=0, Main!$V8465=0, Main!$W8465=0), "", DATE(Main!$U8465, Main!$V8465, Main!$W8465) ) -> 42707 | Y8465: =Table1[[#This Row],[Average_Cost_for_two]]*VLOOKUP(Table1[[#This Row],[Currency]],currency!$A$2:$B$10,2,FALSE) -> 6 | Z8465: =VLOOKUP(C8465,country!A:B,2,FALSE) -> India | AA8465: =ROUNDUP(V8465/3,0) -> 4
A8466: 2300003 | B8466: Anaicha's Food Joint | C8466: 1 | D8466: Kanpur | E8466: 113/187, Swaroop Nagar, Kanpur | F8466: Swaroop Nagar | G8466: Swaroop Nagar, Kanpur | H8466: 80.315628 | I8466: 26.482581 | J8466: Chinese, North Indian, Continental | K8466: Indian Rupees(Rs.) | L8466: No | M8466: No | N8466: No | O8466: No | P8466: 3 | Q8466: 106 | R8466: 850 | S8466: =IF(Table1[[#This Row],[Average_Cost_for_two]]<500,"Low",IF(Table1[[#This Row],[Average_Cost_for_two]]<=1500,"Medium","High")) -> Medium | T8466: 3.6 | U8466: 2018 | V8466: 12 | W8466: 16 | X8466: =IF(OR(Main!$U8466=0, Main!$V8466=0, Main!$W8466=0), "", DATE(Main!$U8466, Main!$V8466, Main!$W8466) ) -> 43450 | Y8466: =Table1[[#This Row],[Average_Cost_for_two]]*VLOOKUP(Table1[[#This Row],[Currency]],currency!$A$2:$B$10,2,FALSE) -> 10.2 | Z8466: =VLOOKUP(C8466,country!A:B,2,FALSE) -> India | AA8466: =ROUNDUP(V8466/3,0) -> 4
A8467: 901004 | B8467: Aangan - Downtown Multicuisine Restaurant | C8467: 1 | D8467: Kochi | E8467: 32/1180C, Civil Lane Road, Palarivattom, Kochi | F8467: Palarivattom | G8467: Palarivattom, Kochi | H8467: 76.307589 | I8467: 10.003064 | J8467: Chinese, Seafood, North Indian, Biryani | K8467: Indian Rupees(Rs.) | L8467: No | M8467: No | N8467: No | O8467: No | P8467: 2 | Q8467: 146 | R8467: 650 | S8467: =IF(Table1[[#This Row],[Average_Cost_for_two]]<500,"Low",IF(Table1[[#This Row],[Average_Cost_for_two]]<=1500,"Medium","High")) -> Medium | T8467: 4.2 | U8467: 2017 | V8467: 12 | W8467: 19 | X8467: =IF(OR(Main!$U8467=0, Main!$V8467=0, Main!$W8467=0), "", DATE(Main!$U8467, Main!$V8467, Main!$W8467) ) -> 43088 | Y8467: =Table1[[#This Row],[Average_Cost_for_two]]*VLOOKUP(Table1[[#This Row],[Currency]],currency!$A$2:$B$10,2,FALSE) -> 7.8 | Z8467: =VLOOKUP(C8467,country!A:B,2,FALSE) -> India | AA8467: =ROUNDUP(V8467/3,0) -> 4
... A8486: 110516 | B8486: The Garden Cafe - The Fern | C8486: 1 | D8486: Ahmedabad | E8486: The Fern, Near Sola Overbridge, S G Highway, Sola, Ahmedabad | F8486: The Fern, Sola | G8486: The Fern, Sola, Ahmedabad | H8486: 72.522217 | I8486: 23.064091 | J8486: North Indian, Italian, Asian, South Indian | K8486: Indian Rupees(Rs.) | L8486: No | M8486: No | N8486: No | O8486: No | P8486: 3 | Q8486: 192 | R8486: 1200 | S8486: =IF(Table1[[#This Row],[Average_Cost_for_two]]<500,"Low",IF(Table1[[#This Row],[Average_Cost_for_two]]<=1500,"Medium","High")) -> Medium | T8486: 4.1 | U8486: 2014 | V8486: 11 | W8486: 28 | X8486: =IF(OR(Main!$U8486=0, Main!$V8486=0, Main!$W8486=0), "", DATE(Main!$U8486, Main!$V8486, Main!$W8486) ) -> 41971 | Y8486: =Table1[[#This Row],[Average_Cost_for_two]]*VLOOKUP(Table1[[#This Row],[Currency]],currency!$A$2:$B$10,2,FALSE) -> 14.4 | Z8486: =VLOOKUP(C8486,country!A:B,2,FALSE) -> India | AA8486: =ROUNDUP(V8486/3,0) -> 4
A8487: 18317988 | B8487: The BrewMaster | C8487: 1 | D8487: Allahabad | E8487: Near Vishal Megamart, Civil Lines, Allahabad | F8487: Civil Lines | G8487: Civil Lines, Allahabad | H8487: 81.832796 | I8487: 25.451646 | J8487: North Indian, Chinese, Italian | K8487: Indian Rupees(Rs.) | L8487: No | M8487: No | N8487: No | O8487: No | P8487: 1 | Q8487: 49 | S8487: =IF(Table1[[#This Row],[Average_Cost_for_two]]<500,"Low",IF(Table1[[#This Row],[Average_Cost_for_two]]<=1500,"Medium","High")) -> Low | T8487: 3.3 | U8487: 2018 | V8487: 11 | W8487: 16 | X8487: =IF(OR(Main!$U8487=0, Main!$V8487=0, Main!$W8487=0), "", DATE(Main!$U8487, Main!$V8487, Main!$W8487) ) -> 43420 | Y8487: =Table1[[#This Row],[Average_Cost_for_two]]*VLOOKUP(Table1[[#This Row],[Currency]],currency!$A$2:$B$10,2,FALSE) -> 0 | Z8487: =VLOOKUP(C8487,country!A:B,2,FALSE) -> India | AA8487: =ROUNDUP(V8487/3,0) -> 4
A8488: 2500054 | B8488: Angeethi Restaurant | C8488: 1 | D8488: Aurangabad | E8488: Seven Hill Flyover, Jalna Road, Vidya Nagar, CIDCO, Aurangabad | F8488: CIDCO | G8488: CIDCO, Aurangabad | H8488: 75.353942 | I8488: 19.874733 | J8488: North Indian, Chinese | K8488: Indian Rupees(Rs.) | L8488: No | M8488: No | N8488: No | O8488: No | P8488: 2 | Q8488: 63 | R8488: 600 | S8488: =IF(Table1[[#This Row],[Average_Cost_for_two]]<500,"Low",IF(Table1[[#This Row],[Average_Cost_for_two]]<=1500,"Medium","High")) -> Medium | T8488: 3.3 | U8488: 2013 | V8488: 11 | W8488: 22 | X8488: =IF(OR(Main!$U8488=0, Main!$V8488=0, Main!$W8488=0), "", DATE(Main!$U8488, Main!$V8488, Main!$W8488) ) -> 41600 | Y8488: =Table1[[#This Row],[Average_Cost_for_two]]*VLOOKUP(Table1[[#This Row],[Currency]],currency!$A$2:$B$10,2,FALSE) -> 7.2 | Z8488: =VLOOKUP(C8488,country!A:B,2,FALSE) -> India | AA8488: =ROUNDUP(V8488/3,0) -> 4
A8489: 2500062 | B8489: Kareem's Fine Dining | C8489: 1 | D8489: Aurangabad | E8489: A1-A3, Motiwala Complex, Below KFC Restaurant, Nirala Bazar, Aurangabad | F8489: Nirala Bazar | G8489: Nirala Bazar, Aurangabad | H8489: 75.323503 | I8489: 19.880256 | J8489: Mughlai, Biryani | K8489: Indian Rupees(Rs.) | L8489: No | M8489: No | N8489: No | O8489: No | P8489: 2 | Q8489: 45 | R8489: 700 | S8489: =IF(Table1[[#This Row],[Average_Cost_for_two]]<500,"Low",IF(Table1[[#This Row],[Average_Cost_for_two]]<=1500,"Medium","High")) -> Medium | T8489: 3.3 | U8489: 2015 | V8489: 11 | W8489: 4 | X8489: =IF(OR(Main!$U8489=0, Main!$V8489=0, Main!$W8489=0), "", DATE(Main!$U8489, Main!$V8489, Main!$W8489) ) -> 42312 | Y8489: =Table1[[#This Row],[Average_Cost_for_two]]*VLOOKUP(Table1[[#This Row],[Currency]],currency!$A$2:$B$10,2,FALSE) -> 8.4 | Z8489: =VLOOKUP(C8489,country!A:B,2,FALSE) -> India | AA8489: =ROUNDUP(V8489/3,0) -> 4
A8490: 18359919 | B8490: Onesta | C8490: 1 | D8490: Bangalore | E8490: Site 15, 15th Cross, 100 Feet Road, 4th Phase, JP Nagar, Bangalore | F8490: JP Nagar | G8490: JP Nagar, Bangalore | H8490: 77.596791 | I8490: 12.906229 | J8490: Pizza, Cafe, Italian | K8490: Indian Rupees(Rs.) | L8490: No | M8490: No | N8490: No | O8490: No | P8490: 2 | Q8490: 781 | R8490: 600 | S8490: =IF(Table1[[#This Row],[Average_Cost_for_two]]<500,"Low",IF(Table1[[#This Row],[Average_Cost_for_two]]<=1500,"Medium","High")) -> Medium | T8490: 4.6 | U8490: 2018 | V8490: 11 | W8490: 2 | X8490: =IF(OR(Main!$U8490=0, Main!$V8490=0, Main!$W8490=0), "", DATE(Main!$U8490, Main!$V8490, Main!$W8490) ) -> 43406 | Y8490: =Table1[[#This Row],[Average_Cost_for_two]]*VLOOKUP(Table1[[#This Row],[Currency]],currency!$A$2:$B$10,2,FALSE) -> 7.2 | Z8490: =VLOOKUP(C8490,country!A:B,2,FALSE) -> India | AA8490: =ROUNDUP(V8490/3,0) -> 4
A8491: 2600025 | B8491: Pizza Hut | C8491: 1 | D8491: Bhopal | E8491: Third Floor, DB City Mall, Arera Hills, Maharana Pratap Nagar, Bhopal | F8491: DB City, Maharana Pratap Nagar | G8491: DB City, Maharana Pratap Nagar, Bhopal | H8491: 77.429845 | I8491: 23.232537 | J8491: Pizza | K8491: Indian Rupees(Rs.) | L8491: No | M8491: No | N8491: No | O8491: No | P8491: 2 | Q8491: 118 | R8491: 650 | S8491: =IF(Table1[[#This Row],[Average_Cost_for_two]]<500,"Low",IF(Table1[[#This Row],[Average_Cost_for_two]]<=1500,"Medium","High")) -> Medium | T8491: 4.1 | U8491: 2015 | V8491: 11 | W8491: 13 | X8491: =IF(OR(Main!$U8491=0, Main!$V8491=0, Main!$W8491=0), "", DATE(Main!$U8491, Main!$V8491, Main!$W8491) ) -> 42321 | Y8491: =Table1[[#This Row],[Average_Cost_for_two]]*VLOOKUP(Table1[[#This Row],[Currency]],currency!$A$2:$B$10,2,FALSE) -> 7.8 | Z8491: =VLOOKUP(C8491,country!A:B,2,FALSE) -> India | AA8491: =ROUNDUP(V8491/3,0) -> 4
A8492: 18235390 | B8492: Brewberrys The Coffee Bar | C8492: 1 | D8492: Bhubaneshwar | E8492: 3, Infocity Road, Patia, Bhubaneshwar | F8492: Patia | G8492: Patia, Bhubaneshwar | H8492: 85.811123 | I8492: 20.343144 | J8492: Cafe | K8492: Indian Rupees(Rs.) | L8492: No | M8492: No | N8492: No | O8492: No | P8492: 1 | Q8492: 197 | R8492: 400 | S8492: =IF(Table1[[#This Row],[Average_Cost_for_two]]<500,"Low",IF(Table1[[#This Row],[Average_Cost_for_two]]<=1500,"Medium","High")) -> Low | T8492: 4 | U8492: 2011 | V8492: 11 | W8492: 5 | X8492: =IF(OR(Main!$U8492=0, Main!$V8492=0, Main!$W8492=0), "", DATE(Main!$U8492, Main!$V8492, Main!$W8492) ) -> 40852 | Y8492: =Table1[[#This Row],[Average_Cost_for_two]]*VLOOKUP(Table1[[#This Row],[Currency]],currency!$A$2:$B$10,2,FALSE) -> 4.8 | Z8492: =VLOOKUP(C8492,country!A:B,2,FALSE) -> India | AA8492: =ROUNDUP(V8492/3,0) -> 4
A8493: 121553 | B8493: Kylin Experience | C8493: 1 | D8493: Chandigarh | E8493: 312 A, 3rd Floor, Elante Mall, Phase 1, Chandigarh Industrial Area, Chandigarh | F8493: Elante Mall, Chandigarh Industrial Area | G8493: Elante Mall, Chandigarh Industrial Area, Chandigarh | H8493: 76.80064 | I8493: 30.70561 | J8493: Japanese, Chinese, Thai, Malaysian, Burmese, Asian | K8493: Indian Rupees(Rs.) | L8493: No | M8493: No | N8493: No | O8493: No | P8493: 3 | Q8493: 300 | R8493: 1600 | S8493: =IF(Table1[[#This Row],[Average_Cost_for_two]]<500,"Low",IF(Table1[[#This Row],[Average_Cost_for_two]]<=1500,"Medium","High")) -> High | T8493: 4.1 | U8493: 2018 | V8493: 11 | W8493: 17 | X8493: =IF(OR(Main!$U8493=0, Main!$V8493=0, Main!$W8493=0), "", DATE(Main!$U8493, Main!$V8493, Main!$W8493) ) -> 43421 | Y8493: =Table1[[#This Row],[Average_Cost_for_two]]*VLOOKUP(Table1[[#This Row],[Currency]],currency!$A$2:$B$10,2,FALSE) -> 19.2 | Z8493: =VLOOKUP(C8493,country!A:B,2,FALSE) -> India | AA8493: =ROUNDUP(V8493/3,0) -> 4
A8494: 121335 | B8494: Pirates Of Grill | C8494: 1 | D8494: Chandigarh | E8494: 313, Third Floor, Elante Mall, Phase 1, Chandigarh Industrial Area, Chandigarh | F8494: Elante Mall, Chandigarh Industrial Area | G8494: Elante Mall, Chandigarh Industrial Area, Chandigarh | H8494: 76.800956 | I8494: 30.705775 | J8494: North Indian, Continental, Asian | K8494: Indian Rupees(Rs.) | L8494: No | M8494: No | N8494: No | O8494: No | P8494: 3 | Q8494: 1022 | R8494: 1200 | S8494: =IF(Table1[[#This Row],[Average_Cost_for_two]]<500,"Low",IF(Table1[[#This Row],[Average_Cost_for_two]]<=1500,"Medium","High")) -> Medium | T8494: 4 | U8494: 2010 | V8494: 11 | W8494: 7 | X8494: =IF(OR(Main!$U8494=0, Main!$V8494=0, Main!$W8494=0), "", DATE(Main!$U8494, Main!$V8494, Main!$W8494) ) -> 40489 | Y8494: =Table1[[#This Row],[Average_Cost_for_two]]*VLOOKUP(Table1[[#This Row],[Currency]],currency!$A$2:$B$10,2,FALSE) -> 14.4 | Z8494: =VLOOKUP(C8494,country!A:B,2,FALSE) -> India | AA8494: =ROUNDUP(V8494/3,0) -> 4
A8495: 120014 | B8495: Barbeque Nation | C8495: 1 | D8495: Chandigarh | E8495: SCO 39, Madhya Marg, Sector 26, Chandigarh | F8495: Sector 26 | G8495: Sector 26, Chandigarh | H8495: 76.805192 | I8495: 30.725704 | J8495: North Indian, Chinese | K8495: Indian Rupees(Rs.) | L8495: No | M8495: No | N8495: No | O8495: No | P8495: 3 | Q8495: 1450 | R8495: 1300 | S8495: =IF(Table1[[#This Row],[Average_Cost_for_two]]<500,"Low",IF(Table1[[#This Row],[Average_Cost_for_two]]<=1500,"Medium","High")) -> Medium | T8495: 4.5 | U8495: 2016 | V8495: 11 | W8495: 23 | X8495: =IF(OR(Main!$U8495=0, Main!$V8495=0, Main!$W8495=0), "", DATE(Main!$U8495, Main!$V8495, Main!$W8495) ) -> 42697 | Y8495: =Table1[[#This Row],[Average_Cost_for_two]]*VLOOKUP(Table1[[#This Row],[Currency]],currency!$A$2:$B$10,2,FALSE) -> 15.6 | Z8495: =VLOOKUP(C8495,country!A:B,2,FALSE) -> India | AA8495: =ROUNDUP(V8495/3,0) -> 4
A8496: 72604 | B8496: Coal Barbecues | C8496: 1 | D8496: Chennai | E8496: 17-18, Rajalakshmi Nagar, 7th Cross Street, 100 Feet Bypass Road, Velachery, Chennai | F8496: Velachery | G8496: Velachery, Chennai | H8496: 80.218114 | I8496: 12.986047 | J8496: North Indian, Mediterranean, Asian, Arabian | K8496: Indian Rupees(Rs.) | L8496: No | M8496: No | N8496: No | O8496: No | P8496: 3 | Q8496: 1267 | R8496: 1400 | S8496: =IF(Table1[[#This Row],[Average_Cost_for_two]]<500,"Low",IF(Table1[[#This Row],[Average_Cost_for_two]]<=1500,"Medium","High")) -> Medium | T8496: 4.6 | U8496: 2018 | V8496: 11 | W8496: 28 | X8496: =IF(OR(Main!$U8496=0, Main!$V8496=0, Main!$W8496=0), "", DATE(Main!$U8496, Main!$V8496, Main!$W8496) ) -> 43432 | Y8496: =Table1[[#This Row],[Average_Cost_for_two]]*VLOOKUP(Table1[[#This Row],[Currency]],currency!$A$2:$B$10,2,FALSE) -> 16.8 | Z8496: =VLOOKUP(C8496,country!A:B,2,FALSE) -> India | AA8496: =ROUNDUP(V8496/3,0) -> 4
A8497: 3000001 | B8497: That's Y Food | C8497: 1 | D8497: Coimbatore | E8497: 24/49, TV Swamy Road East, Opposite Emeral Building, RS Puram, Coimbatore | F8497: RS Puram | G8497: RS Puram, Coimbatore | H8497: 76.95295 | I8497: 11.010375 | J8497: North Indian, Biryani | K8497: Indian Rupees(Rs.) | L8497: No | M8497: No | N8497: No | O8497: No | P8497: 3 | Q8497: 299 | R8497: 1400 | S8497: =IF(Table1[[#This Row],[Average_Cost_for_two]]<500,"Low",IF(Table1[[#This Row],[Average_Cost_for_two]]<=1500,"Medium","High")) -> Medium | T8497: 4.2 | U8497: 2018 | V8497: 11 | W8497: 4 | X8497: =IF(OR(Main!$U8497=0, Main!$V8497=0, Main!$W8497=0), "", DATE(Main!$U8497, Main!$V8497, Main!$W8497) ) -> 43408 | Y8497: =Table1[[#This Row],[Average_Cost_for_two]]*VLOOKUP(Table1[[#This Row],[Currency]],currency!$A$2:$B$10,2,FALSE) -> 16.8 | Z8497: =VLOOKUP(C8497,country!A:B,2,FALSE) -> India | AA8497: =ROUNDUP(V8497/3,0) -> 4
A8498: 18168161 | B8498: Domino's Pizza | C8498: 1 | D8498: Ghaziabad | E8498: Shop 18, Lower Ground, Shipra Mall, Indirapuram, Ghaziabad | F8498: Shipra Mall, Indirapuram | G8498: Shipra Mall, Indirapuram, Ghaziabad | H8498: 77.369815 | I8498: 28.634078 | J8498: Pizza, Fast Food | K8498: Indian Rupees(Rs.) | L8498: No | M8498: No | N8498: No | O8498: No | P8498: 2 | Q8498: 17 | R8498: 700 | S8498: =IF(Table1[[#This Row],[Average_Cost_for_two]]<500,"Low",IF(Table1[[#This Row],[Average_Cost_for_two]]<=1500,"Medium","High")) -> Medium | T8498: 3.2 | U8498: 2017 | V8498: 11 | W8498: 2 | X8498: =IF(OR(Main!$U8498=0, Main!$V8498=0, Main!$W8498=0), "", DATE(Main!$U8498, Main!$V8498, Main!$W8498) ) -> 43041 | Y8498: =Table1[[#This Row],[Average_Cost_for_two]]*VLOOKUP(Table1[[#This Row],[Currency]],currency!$A$2:$B$10,2,FALSE) -> 8.4 | Z8498: =VLOOKUP(C8498,country!A:B,2,FALSE) -> India | AA8498: =ROUNDUP(V8498/3,0) -> 4
A8499: 18384506 | B8499: The Basement Cafí© | C8499: 1 | D8499: Guwahati | E8499: R.G. Baruah Road, Near Guwahati Commerece College, Chandmari, Guwahati | F8499: Chandmari | G8499: Chandmari, Guwahati | H8499: 91.775246 | I8499: 26.180243 | J8499: Cafe | K8499: Indian Rupees(Rs.) | L8499: No | M8499: No | N8499: No | O8499: No | P8499: 2 | Q8499: 126 | R8499: 600 | S8499: =IF(Table1[[#This Row],[Average_Cost_for_two]]<500,"Low",IF(Table1[[#This Row],[Average_Cost_for_two]]<=1500,"Medium","High")) -> Medium | T8499: 4.7 | U8499: 2014 | V8499: 11 | W8499: 12 | X8499: =IF(OR(Main!$U8499=0, Main!$V8499=0, Main!$W8499=0), "", DATE(Main!$U8499, Main!$V8499, Main!$W8499) ) -> 41955 | Y8499: =Table1[[#This Row],[Average_Cost_for_two]]*VLOOKUP(Table1[[#This Row],[Currency]],currency!$A$2:$B$10,2,FALSE) -> 7.2 | Z8499: =VLOOKUP(C8499,country!A:B,2,FALSE) -> India | AA8499: =ROUNDUP(V8499/3,0) -> 4
... A8532: 1400555 | B8532: Cafe Terazza | C8532: 1 | D8532: Indore | E8532: 10th Floor, Airen Heights, Opposite C 21 Mall, Vijay Nagar, Indore | F8532: Vijay Nagar | G8532: Vijay Nagar, Indore | H8532: 75.892471 | I8532: 22.745049 | J8532: Cafe, Italian, Mexican, Chinese | K8532: Indian Rupees(Rs.) | L8532: No | M8532: No | N8532: No | O8532: No | P8532: 2 | Q8532: 502 | R8532: 700 | S8532: =IF(Table1[[#This Row],[Average_Cost_for_two]]<500,"Low",IF(Table1[[#This Row],[Average_Cost_for_two]]<=1500,"Medium","High")) -> Medium | T8532: 3.9 | U8532: 2014 | V8532: 10 | W8532: 10 | X8532: =IF(OR(Main!$U8532=0, Main!$V8532=0, Main!$W8532=0), "", DATE(Main!$U8532, Main!$V8532, Main!$W8532) ) -> 41922 | Y8532: =Table1[[#This Row],[Average_Cost_for_two]]*VLOOKUP(Table1[[#This Row],[Currency]],currency!$A$2:$B$10,2,FALSE) -> 8.4 | Z8532: =VLOOKUP(C8532,country!A:B,2,FALSE) -> India | AA8532: =ROUNDUP(V8532/3,0) -> 4
A8533: 2300497 | B8533: Atmosphere Grill Cafe Sheesha | C8533: 1 | D8533: Kanpur | E8533: 8th Floor, J.S. Tower, 16/106 - Mall Road, Kanpur, Mall Road, Kanpur | F8533: Mall Road | G8533: Mall Road, Kanpur | H8533: 80.354002 | I8533: 26.472001 | J8533: Indian, Chinese, Continental | K8533: Indian Rupees(Rs.) | L8533: No | M8533: No | N8533: No | O8533: No | P8533: 1 | Q8533: 34 | S8533: =IF(Table1[[#This Row],[Average_Cost_for_two]]<500,"Low",IF(Table1[[#This Row],[Average_Cost_for_two]]<=1500,"Medium","High")) -> Low | T8533: 3.6 | U8533: 2012 | V8533: 10 | W8533: 27 | X8533: =IF(OR(Main!$U8533=0, Main!$V8533=0, Main!$W8533=0), "", DATE(Main!$U8533, Main!$V8533, Main!$W8533) ) -> 41209 | Y8533: =Table1[[#This Row],[Average_Cost_for_two]]*VLOOKUP(Table1[[#This Row],[Currency]],currency!$A$2:$B$10,2,FALSE) -> 0 | Z8533: =VLOOKUP(C8533,country!A:B,2,FALSE) -> India | AA8533: =ROUNDUP(V8533/3,0) -> 4
A8534: 2300018 | B8534: Little Chef | C8534: 1 | D8534: Kanpur | E8534: 15/198- A, Near Civil Court, Civil Lines, Near, Mall Road, Kanpur | F8534: Mall Road | G8534: Mall Road, Kanpur | H8534: 80.351569 | I8534: 26.47775 | J8534: North Indian, Fast Food | K8534: Indian Rupees(Rs.) | L8534: No | M8534: No | N8534: No | O8534: No | P8534: 3 | Q8534: 158 | R8534: 1000 | S8534: =IF(Table1[[#This Row],[Average_Cost_for_two]]<500,"Low",IF(Table1[[#This Row],[Average_Cost_for_two]]<=1500,"Medium","High")) -> Medium | T8534: 4.1 | U8534: 2011 | V8534: 10 | W8534: 15 | X8534: =IF(OR(Main!$U8534=0, Main!$V8534=0, Main!$W8534=0), "", DATE(Main!$U8534, Main!$V8534, Main!$W8534) ) -> 40831 | Y8534: =Table1[[#This Row],[Average_Cost_for_two]]*VLOOKUP(Table1[[#This Row],[Currency]],currency!$A$2:$B$10,2,FALSE) -> 12 | Z8534: =VLOOKUP(C8534,country!A:B,2,FALSE) -> India | AA8534: =ROUNDUP(V8534/3,0) -> 4
A8535: 95256 | B8535: Kashi Art Cafe | C8535: 1 | D8535: Kochi | E8535: Burgher Street, Fort Kochi, Kochi | F8535: Fort Kochi | G8535: Fort Kochi, Kochi | H8535: 76.242981 | I8535: 9.9667833 | J8535: European, Cafe | K8535: Indian Rupees(Rs.) | L8535: No | M8535: No | N8535: No | O8535: No | P8535: 2 | Q8535: 659 | R8535: 600 | S8535: =IF(Table1[[#This Row],[Average_Cost_for_two]]<500,"Low",IF(Table1[[#This Row],[Average_Cost_for_two]]<=1500,"Medium","High")) -> Medium | T8535: 4.2 | U8535: 2011 | V8535: 10 | W8535: 28 | X8535: =IF(OR(Main!$U8535=0, Main!$V8535=0, Main!$W8535=0), "", DATE(Main!$U8535, Main!$V8535, Main!$W8535) ) -> 40844 | Y8535: =Table1[[#This Row],[Average_Cost_for_two]]*VLOOKUP(Table1[[#This Row],[Currency]],currency!$A$2:$B$10,2,FALSE) -> 7.2 | Z8535: =VLOOKUP(C8535,country!A:B,2,FALSE) -> India | AA8535: =ROUNDUP(V8535/3,0) -> 4
A8536: 901035 | B8536: Palaaram | C8536: 1 | D8536: Kochi | E8536: Vallathol Junction, Thrikkakara, Kakkanad, Kochi | F8536: Kakkanad | G8536: Kakkanad, Kochi | H8536: 76.336958 | I8536: 10.035573 | J8536: Kerala, Fast Food | K8536: Indian Rupees(Rs.) | L8536: No | M8536: No | N8536: No | O8536: No | P8536: 2 | Q8536: 105 | R8536: 550 | S8536: =IF(Table1[[#This Row],[Average_Cost_for_two]]<500,"Low",IF(Table1[[#This Row],[Average_Cost_for_two]]<=1500,"Medium","High")) -> Medium | T8536: 3.7 | U8536: 2018 | V8536: 10 | W8536: 1 | X8536: =IF(OR(Main!$U8536=0, Main!$V8536=0, Main!$W8536=0), "", DATE(Main!$U8536, Main!$V8536, Main!$W8536) ) -> 43374 | Y8536: =Table1[[#This Row],[Average_Cost_for_two]]*VLOOKUP(Table1[[#This Row],[Currency]],currency!$A$2:$B$10,2,FALSE) -> 6.6 | Z8536: =VLOOKUP(C8536,country!A:B,2,FALSE) -> India | AA8536: =ROUNDUP(V8536/3,0) -> 4
...

Sheet country
A1: CountryID | B1: Countryname
A2: 1 | B2: India
A3: 14 | B3: Australia
A4: 30 | B4: Brazil
A5: 37 | B5: Canada
A6: 94 | B6: Indonasia
A7: 148 | B7: New Zealand
A8: 162 | B8: Phillipines
A9: 166 | B9: Qatar
A10: 184 | B10: Singapore
A11: 189 | B11: South Africa
A12: 191 | B12: Sri lanka
A13: 208 | B13: Turkey
... A16: 216 | B16: United States

Sheet currency
A1: Currency | B1: USD Rate
A2: Indian Rupees(Rs.) | B2: 0.012
A3: Dollar($) | B3: 1
A4: Pounds(Œ£) | B4: 1.24
A5: NewZealand($) | B5: 0.6
A6: Emirati Diram(AED) | B6: 0.27
A7: Brazilian Real(R$) | B7: 0.2
A8: Turkish Lira(TL) | B8: 0.05
A9: Qatari Rial(QR) | B9: 0.27
A10: Rand(R) | B10: 0.051
A11: Botswana Pula(P) | B11: 0.073
A12: Sri Lankan Rupee(LKR) | B12: 0.0034
A13: Indonesian Rupiah(IDR) | B13: 6.7e-05

Sheet Date
A1: DateKey | B1: Year | C1: Monthno | D1: Monthfullname | E1: Quarter | F1: YearMonth | G1: Weekdayno | H1: Weekdayname | I1: FinancialMonth | J1: Financial Quarter | N1: Min date | O1: =MIN(Main!$X$1:$X$9553) -> 40179
A2: =IF($O$1+ROW(A1)-1<=$O$3,$O$1+ROW(A1)-1,"") -> 40179 | B2: =YEAR(A2) -> 2010 | C2: =MONTH(A2) -> 1 | D2: =TEXT(A2,"mmmm") -> January | E2: ="Q"&ROUNDUP(MONTH(A2)/3,0) -> Q1 | F2: =TEXT(A2,"yyyy-mmm") -> 2010-Jan | G2: =WEEKDAY(A2,2) -> 5 | H2: =TEXT(A2,"dddd") -> Friday | I2: ="FM"&MOD(MONTH(A2)-4,12)+1 -> FM10 | J2: ="FQ-" & INT((MOD(MONTH(A2)-4,12)/3)+1) -> FQ-4
A3: =IF($O$1+ROW(A2)-1<=$O$3,$O$1+ROW(A2)-1,"") -> 40180 | B3: =YEAR(A3) -> 2010 | C3: =MONTH(A3) -> 1 | D3: =TEXT(A3,"mmmm") -> January | E3: ="Q"&ROUNDUP(MONTH(A3)/3,0) -> Q1 | F3: =TEXT(A3,"yyyy-mmm") -> 2010-Jan | G3: =WEEKDAY(A3,2) -> 6 | H3: =TEXT(A3,"dddd") -> Saturday | I3: ="FM"&MOD(MONTH(A3)-4,12)+1 -> FM10 | J3: ="FQ-" & INT((MOD(MONTH(A3)-4,12)/3)+1) -> FQ-4 | N3: Max date | O3: =MAX(Main!$X$2:$X$9552) -> 43462
A4: =IF($O$1+ROW(A3)-1<=$O$3,$O$1+ROW(A3)-1,"") -> 40181 | B4: =YEAR(A4) -> 2010 | C4: =MONTH(A4) -> 1 | D4: =TEXT(A4,"mmmm") -> January | E4: ="Q"&ROUNDUP(MONTH(A4)/3,0) -> Q1 | F4: =TEXT(A4,"yyyy-mmm") -> 2010-Jan | G4: =WEEKDAY(A4,2) -> 7 | H4: =TEXT(A4,"dddd") -> Sunday | I4: ="FM"&MOD(MONTH(A4)-4,12)+1 -> FM10 | J4: ="FQ-" & INT((MOD(MONTH(A4)-4,12)/3)+1) -> FQ-4
A5: =IF($O$1+ROW(A4)-1<=$O$3,$O$1+ROW(A4)-1,"") -> 40182 | B5: =YEAR(A5) -> 2010 | C5: =MONTH(A5) -> 1 | D5: =TEXT(A5,"mmmm") -> January | E5: ="Q"&ROUNDUP(MONTH(A5)/3,0) -> Q1 | F5: =TEXT(A5,"yyyy-mmm") -> 2010-Jan | G5: =WEEKDAY(A5,2) -> 1 | H5: =TEXT(A5,"dddd") -> Monday | I5: ="FM"&MOD(MONTH(A5)-4,12)+1 -> FM10 | J5: ="FQ-" & INT((MOD(MONTH(A5)-4,12)/3)+1) -> FQ-4
A6: =IF($O$1+ROW(A5)-1<=$O$3,$O$1+ROW(A5)-1,"") -> 40183 | B6: =YEAR(A6) -> 2010 | C6: =MONTH(A6) -> 1 | D6: =TEXT(A6,"mmmm") -> January | E6: ="Q"&ROUNDUP(MONTH(A6)/3,0) -> Q1 | F6: =TEXT(A6,"yyyy-mmm") -> 2010-Jan | G6: =WEEKDAY(A6,2) -> 2 | H6: =TEXT(A6,"dddd") -> Tuesday | I6: ="FM"&MOD(MONTH(A6)-4,12)+1 -> FM10 | J6: ="FQ-" & INT((MOD(MONTH(A6)-4,12)/3)+1) -> FQ-4
A7: =IF($O$1+ROW(A6)-1<=$O$3,$O$1+ROW(A6)-1,"") -> 40184 | B7: =YEAR(A7) -> 2010 | C7: =MONTH(A7) -> 1 | D7: =TEXT(A7,"mmmm") -> January | E7: ="Q"&ROUNDUP(MONTH(A7)/3,0) -> Q1 | F7: =TEXT(A7,"yyyy-mmm") -> 2010-Jan | G7: =WEEKDAY(A7,2) -> 3 | H7: =TEXT(A7,"dddd") -> Wednesday | I7: ="FM"&MOD(MONTH(A7)-4,12)+1 -> FM10 | J7: ="FQ-" & INT((MOD(MONTH(A7)-4,12)/3)+1) -> FQ-4
A8: =IF($O$1+ROW(A7)-1<=$O$3,$O$1+ROW(A7)-1,"") -> 40185 | B8: =YEAR(A8) -> 2010 | C8: =MONTH(A8) -> 1 | D8: =TEXT(A8,"mmmm") -> January | E8: ="Q"&ROUNDUP(MONTH(A8)/3,0) -> Q1 | F8: =TEXT(A8,"yyyy-mmm") -> 2010-Jan | G8: =WEEKDAY(A8,2) -> 4 | H8: =TEXT(A8,"dddd") -> Thursday | I8: ="FM"&MOD(MONTH(A8)-4,12)+1 -> FM10 | J8: ="FQ-" & INT((MOD(MONTH(A8)-4,12)/3)+1) -> FQ-4
A9: =IF($O$1+ROW(A8)-1<=$O$3,$O$1+ROW(A8)-1,"") -> 40186 | B9: =YEAR(A9) -> 2010 | C9: =MONTH(A9) -> 1 | D9: =TEXT(A9,"mmmm") -> January | E9: ="Q"&ROUNDUP(MONTH(A9)/3,0) -> Q1 | F9: =TEXT(A9,"yyyy-mmm") -> 2010-Jan | G9: =WEEKDAY(A9,2) -> 5 | H9: =TEXT(A9,"dddd") -> Friday | I9: ="FM"&MOD(MONTH(A9)-4,12)+1 -> FM10 | J9: ="FQ-" & INT((MOD(MONTH(A9)-4,12)/3)+1) -> FQ-4
A10: =IF($O$1+ROW(A9)-1<=$O$3,$O$1+ROW(A9)-1,"") -> 40187 | B10: =YEAR(A10) -> 2010 | C10: =MONTH(A10) -> 1 | D10: =TEXT(A10,"mmmm") -> January | E10: ="Q"&ROUNDUP(MONTH(A10)/3,0) -> Q1 | F10: =TEXT(A10,"yyyy-mmm") -> 2010-Jan | G10: =WEEKDAY(A10,2) -> 6 | H10: =TEXT(A10,"dddd") -> Saturday | I10: ="FM"&MOD(MONTH(A10)-4,12)+1 -> FM10 | J10: ="FQ-" & INT((MOD(MONTH(A10)-4,12)/3)+1) -> FQ-4
A11: =IF($O$1+ROW(A10)-1<=$O$3,$O$1+ROW(A10)-1,"") -> 40188 | B11: =YEAR(A11) -> 2010 | C11: =MONTH(A11) -> 1 | D11: =TEXT(A11,"mmmm") -> January | E11: ="Q"&ROUNDUP(MONTH(A11)/3,0) -> Q1 | F11: =TEXT(A11,"yyyy-mmm") -> 2010-Jan | G11: =WEEKDAY(A11,2) -> 7 | H11: =TEXT(A11,"dddd") -> Sunday | I11: ="FM"&MOD(MONTH(A11)-4,12)+1 -> FM10 | J11: ="FQ-" & INT((MOD(MONTH(A11)-4,12)/3)+1) -> FQ-4
A12: =IF($O$1+ROW(A11)-1<=$O$3,$O$1+ROW(A11)-1,"") -> 40189 | B12: =YEAR(A12) -> 2010 | C12: =MONTH(A12) -> 1 | D12: =TEXT(A12,"mmmm") -> January | E12: ="Q"&ROUNDUP(MONTH(A12)/3,0) -> Q1 | F12: =TEXT(A12,"yyyy-mmm") -> 2010-Jan | G12: =WEEKDAY(A12,2) -> 1 | H12: =TEXT(A12,"dddd") -> Monday | I12: ="FM"&MOD(MONTH(A12)-4,12)+1 -> FM10 | J12: ="FQ-" & INT((MOD(MONTH(A12)-4,12)/3)+1) -> FQ-4
A13: =IF($O$1+ROW(A12)-1<=$O$3,$O$1+ROW(A12)-1,"") -> 40190 | B13: =YEAR(A13) -> 2010 | C13: =MONTH(A13) -> 1 | D13: =TEXT(A13,"mmmm") -> January | E13: ="Q"&ROUNDUP(MONTH(A13)/3,0) -> Q1 | F13: =TEXT(A13,"yyyy-mmm") -> 2010-Jan | G13: =WEEKDAY(A13,2) -> 2 | H13: =TEXT(A13,"dddd") -> Tuesday | I13: ="FM"&MOD(MONTH(A13)-4,12)+1 -> FM10 | J13: ="FQ-" & INT((MOD(MONTH(A13)-4,12)/3)+1) -> FQ-4
A14: =IF($O$1+ROW(A13)-1<=$O$3,$O$1+ROW(A13)-1,"") -> 40191 | B14: =YEAR(A14) -> 2010 | C14: =MONTH(A14) -> 1 | D14: =TEXT(A14,"mmmm") -> January | E14: ="Q"&ROUNDUP(MONTH(A14)/3,0) -> Q1 | F14: =TEXT(A14,"yyyy-mmm") -> 2010-Jan | G14: =WEEKDAY(A14,2) -> 3 | H14: =TEXT(A14,"dddd") -> Wednesday | I14: ="FM"&MOD(MONTH(A14)-4,12)+1 -> FM10 | J14: ="FQ-" & INT((MOD(MONTH(A14)-4,12)/3)+1) -> FQ-4
A15: =IF($O$1+ROW(A14)-1<=$O$3,$O$1+ROW(A14)-1,"") -> 40192 | B15: =YEAR(A15) -> 2010 | C15: =MONTH(A15) -> 1 | D15: =TEXT(A15,"mmmm") -> January | E15: ="Q"&ROUNDUP(MONTH(A15)/3,0) -> Q1 | F15: =TEXT(A15,"yyyy-mmm") -> 2010-Jan | G15: =WEEKDAY(A15,2) -> 4 | H15: =TEXT(A15,"dddd") -> Thursday | I15: ="FM"&MOD(MONTH(A15)-4,12)+1 -> FM10 | J15: ="FQ-" & INT((MOD(MONTH(A15)-4,12)/3)+1) -> FQ-4
... A3285: =IF($O$1+ROW(A3284)-1<=$O$3,$O$1+ROW(A3284)-1,"") -> 43462 | B3285: =YEAR(A3285) -> 2018 | C3285: =MONTH(A3285) -> 12 | D3285: =TEXT(A3285,"mmmm") -> December | E3285: ="Q"&ROUNDUP(MONTH(A3285)/3,0) -> Q4 | F3285: =TEXT(A3285,"yyyy-mmm") -> 2018-Dec | G3285: =WEEKDAY(A3285,2) -> 5 | H3285: =TEXT(A3285,"dddd") -> Friday | I3285: ="FM"&MOD(MONTH(A3285)-4,12)+1 -> FM9 | J3285: ="FQ-" & INT((MOD(MONTH(A3285)-4,12)/3)+1) -> FQ-3
A3286: =IF($O$1+ROW(A3285)-1<=$O$3,$O$1+ROW(A3285)-1,"")
A3288: =IF($O$1+ROW(A3287)-1<=$O$3,$O$1+ROW(A3287)-1,"")
A3289: =IF($O$1+ROW(A3288)-1<=$O$3,$O$1+ROW(A3288)-1,"")
A3290: =IF($O$1+ROW(A3289)-1<=$O$3,$O$1+ROW(A3289)-1,"")
A3291: =IF($O$1+ROW(A3290)-1<=$O$3,$O$1+ROW(A3290)-1,"")
A3292: =IF($O$1+ROW(A3291)-1<=$O$3,$O$1+ROW(A3291)-1,"")
A3293: =IF($O$1+ROW(A3292)-1<=$O$3,$O$1+ROW(A3292)-1,"")
A3294: =IF($O$1+ROW(A3293)-1<=$O$3,$O$1+ROW(A3293)-1,"")
A3295: =IF($O$1+ROW(A3294)-1<=$O$3,$O$1+ROW(A3294)-1,"")
A3296: =IF($O$1+ROW(A3295)-1<=$O$3,$O$1+ROW(A3295)-1,"")
A3297: =IF($O$1+ROW(A3296)-1<=$O$3,$O$1+ROW(A3296)-1,"")
A3298: =IF($O$1+ROW(A3297)-1<=$O$3,$O$1+ROW(A3297)-1,"")
... A4494: =IF($O$1+ROW(A4493)-1<=$O$3,$O$1+ROW(A4493)-1,"")

Sheet 4
A3: Row Labels | B3: Count of RestaurantID
A4: Australia | B4: 24
A5: Brazil | B5: 60
A6: Canada | B6: 4
A7: India | B7: 8652
A8: Indonasia | B8: 21
A9: New Zealand | B9: 40
A10: Phillipines | B10: 22
A11: Qatar | B11: 20
A12: Singapore | B12: 20
A13: South Africa | B13: 60
A14: Sri lanka | B14: 20
A15: Turkey | B15: 34
... A19: Grand Total | B19: 9551

Sheet 5
A3: Row Labels | B3: Count of RestaurantID
A4: 2010 | B4: 1080
A5: 2011 | B5: 1098
A6: 2012 | B6: 1022
A7: 2013 | B7: 1061
A8: 2014 | B8: 1051
A9: 2015 | B9: 1024
A10: 2016 | B10: 1027
A11: 2017 | B11: 1086
A12: 2018 | B12: 1102
A13: Grand Total | B13: 9551

Sheet 6
A3: Average Ratings | B3: Count of RestaurantID
A4: 4.5 | B4: 95
A5: 4.6 | B5: 78
A6: 4.9 | B6: 61
A7: 4.7 | B7: 42
A8: 4.8 | B8: 25
A9: Grand Total | B9: 301

Sheet 7
A3: Row Labels | B3: Count of RestaurantID
A4: High | B4: 0.06114543
A5: Low | B5: 0.54172338
A6: Medium | B6: 0.39713119
A7: Grand Total | B7: 1

Sheet 8
A3: Row Labels | B3: Count of RestaurantID
A4: No | B4: 0.87875615
A5: Yes | B5: 0.12124385
A6: Grand Total | B6: 1

Sheet 9
A3: Has_Online_delivery | B3: Count of RestaurantName
A4: No | B4: 0.74337766
A5: Yes | B5: 0.25662234
A6: Grand Total | B6: 1

Sheet Q 10; City
A3: City | B3: Average of Average_Cost_for_two
A4: Jakarta | B4: 308437.5
A5: Tangerang | B5: 250000
A6: Bogor | B6: 160000
A7: Bandung | B7: 150000
A8: Colombo | B8: 2375
A9: Pune | B9: 1337.5
A10: Gurgaon | B10: 714.0161
A11: New Delhi | B11: 596.08807
A12: Noida | B12: 539.49074
A13: Faridabad | B13: 447.60956
A14: Grand Total | B14: 1344.7213

Sheet Q 10; Cuisines
A3: Cuisines | B3: Count of RestaurantID
A4: North Indian | B4: 936
A5: North Indian, Chinese | B5: 511
A6: Fast Food | B6: 354
A7: Chinese | B7: 354
A8: North Indian, Mughlai | B8: 334
A9: Grand Total | B9: 2489

Sheet 10Rating
A3: Average of Rating | B3: Distinct Count of City | C3: Distinct Count of countryname
A4: 2.8912679 | B4: 142 | C4: 16
A6: ='10Rating'!A$4 -> 2.8912679 | B6: ='10Rating'!B$4 -> 142 | C6: ='10Rating'!C$4 -> 16

Sheet Dashboard
